{"api":{"name":"listener","title":"Listener","description":"Golang HTTP service listening for Callback and Timeout URLs","version":"1.0","servers":{"listener":{"name":"listener","description":"listener hosts all Listener Services.","services":["swagger","health","mpesa"],"hosts":{"local":{"name":"local","server":"listener","description":"Localhost","uris":["http://localhost:8000"]}}}},"terms":"https://github.com/wondenge/mpesa-listener/blob/master/LICENSE","contact":{"name":"William Ondenge","email":"ondengew@gmail.com","url":"https://www.ondenge.me"},"license":{"name":"Apache License","url":"https://github.com/wondenge/mpesa-listener/blob/master/LICENSE"},"docs":{"description":"Library Usage","url":"https://github.com/wondenge/mpesa-listener/blob/master/README.md"}},"services":{"health":{"name":"health","methods":{"show":{"name":"show","description":"Health check endpoint.","payload":{"type":{"$ref":"#/definitions/Empty"},"example":{}},"result":{"type":{"type":"string"},"example":"Possimus praesentium."}}}},"mpesa":{"name":"mpesa","methods":{"AccountBalanceResult":{"name":"AccountBalanceResult","description":"Account Balance Result URL","payload":{"type":{"$ref":"#/definitions/AccountBalanceResult"},"example":{"Result":{"ConversationId":"236543-276372-2","OriginatorConversationId":"AG_2376487236_126732989KJHJKH","ReferenceData":{"ReferenceItem":{"QueueTimeoutURL":"https://internalsandbox.safaricom.co.ke/mpesa/abresults/v1/submit"}},"ResultCode":0,"ResultDesc":"Initiator information is invalid","ResultParameters":{"ResultParameter":[{"AccountBalance":"Working Account|KES|46713.00|46713.00|0.00|0.00\u0026Float Account|KES|0.00|0.00|0.00|0.00\u0026Utility Account|KES|49217.00|49217.00|0.00|0.00\u0026Charges Paid Account|KES|-220.00|-220.00|0.00|0.00\u0026Organization Settlement Account|KES|0.00|0.00|0.00|0.00","BOCompletedTime":"20170728095642"},{"AccountBalance":"Working Account|KES|46713.00|46713.00|0.00|0.00\u0026Float Account|KES|0.00|0.00|0.00|0.00\u0026Utility Account|KES|49217.00|49217.00|0.00|0.00\u0026Charges Paid Account|KES|-220.00|-220.00|0.00|0.00\u0026Organization Settlement Account|KES|0.00|0.00|0.00|0.00","BOCompletedTime":"20170728095642"},{"AccountBalance":"Working Account|KES|46713.00|46713.00|0.00|0.00\u0026Float Account|KES|0.00|0.00|0.00|0.00\u0026Utility Account|KES|49217.00|49217.00|0.00|0.00\u0026Charges Paid Account|KES|-220.00|-220.00|0.00|0.00\u0026Organization Settlement Account|KES|0.00|0.00|0.00|0.00","BOCompletedTime":"20170728095642"},{"AccountBalance":"Working Account|KES|46713.00|46713.00|0.00|0.00\u0026Float Account|KES|0.00|0.00|0.00|0.00\u0026Utility Account|KES|49217.00|49217.00|0.00|0.00\u0026Charges Paid Account|KES|-220.00|-220.00|0.00|0.00\u0026Organization Settlement Account|KES|0.00|0.00|0.00|0.00","BOCompletedTime":"20170728095642"}]},"ResultType":0,"TransactionID":"LHG31AA5TX"}}},"result":{"type":{"type":"string"},"example":"Quod iusto dignissimos."}},"AccountBalanceTimeout":{"name":"AccountBalanceTimeout","description":"Account Balance Queue TimeOut URL","payload":{"type":{"$ref":"#/definitions/AccountBalanceResult"},"example":{"Result":{"ConversationId":"236543-276372-2","OriginatorConversationId":"AG_2376487236_126732989KJHJKH","ReferenceData":{"ReferenceItem":{"QueueTimeoutURL":"https://internalsandbox.safaricom.co.ke/mpesa/abresults/v1/submit"}},"ResultCode":0,"ResultDesc":"Initiator information is invalid","ResultParameters":{"ResultParameter":[{"AccountBalance":"Working Account|KES|46713.00|46713.00|0.00|0.00\u0026Float Account|KES|0.00|0.00|0.00|0.00\u0026Utility Account|KES|49217.00|49217.00|0.00|0.00\u0026Charges Paid Account|KES|-220.00|-220.00|0.00|0.00\u0026Organization Settlement Account|KES|0.00|0.00|0.00|0.00","BOCompletedTime":"20170728095642"},{"AccountBalance":"Working Account|KES|46713.00|46713.00|0.00|0.00\u0026Float Account|KES|0.00|0.00|0.00|0.00\u0026Utility Account|KES|49217.00|49217.00|0.00|0.00\u0026Charges Paid Account|KES|-220.00|-220.00|0.00|0.00\u0026Organization Settlement Account|KES|0.00|0.00|0.00|0.00","BOCompletedTime":"20170728095642"},{"AccountBalance":"Working Account|KES|46713.00|46713.00|0.00|0.00\u0026Float Account|KES|0.00|0.00|0.00|0.00\u0026Utility Account|KES|49217.00|49217.00|0.00|0.00\u0026Charges Paid Account|KES|-220.00|-220.00|0.00|0.00\u0026Organization Settlement Account|KES|0.00|0.00|0.00|0.00","BOCompletedTime":"20170728095642"},{"AccountBalance":"Working Account|KES|46713.00|46713.00|0.00|0.00\u0026Float Account|KES|0.00|0.00|0.00|0.00\u0026Utility Account|KES|49217.00|49217.00|0.00|0.00\u0026Charges Paid Account|KES|-220.00|-220.00|0.00|0.00\u0026Organization Settlement Account|KES|0.00|0.00|0.00|0.00","BOCompletedTime":"20170728095642"}]},"ResultType":0,"TransactionID":"LHG31AA5TX"}}},"result":{"type":{"type":"string"},"example":"Est non inventore hic explicabo."}},"B2CResult":{"name":"B2CResult","description":"B2C Result URL","payload":{"type":{"$ref":"#/definitions/B2CPaymentResult"},"example":{"ReferenceData":{"ReferenceItem":{"QueueTimeoutURL":"https://internalsandbox.safaricom.co.ke/mpesa/b2cresults/v1/submit"}},"Result":{"ConversationId":"236543-276372-2","OriginatorConversationId":"AG_2376487236_126732989KJHJKH","ResultCode":0,"ResultDesc":"Initiator information is invalid","ResultType":0,"TransactionID":"LHG31AA5TX"},"ResultParameters":{"ResultParameter":[{"B2CChargesPaidAccountAvailableFunds":236543.9,"B2CRecipientIsRegisteredCustomer":"Y","B2CUtilityAccountAvailableFunds":23654.5,"B2CWorkingAccountAvailableFunds":2000,"ReceiverPartyPublicName":"254722000000 - Safaricom PLC","TransactionAmount":8000,"TransactionCompletedDateTime":"17.07.2017 10:54:57","TransactionReceipt":"LGH3197RIB"},{"B2CChargesPaidAccountAvailableFunds":236543.9,"B2CRecipientIsRegisteredCustomer":"Y","B2CUtilityAccountAvailableFunds":23654.5,"B2CWorkingAccountAvailableFunds":2000,"ReceiverPartyPublicName":"254722000000 - Safaricom PLC","TransactionAmount":8000,"TransactionCompletedDateTime":"17.07.2017 10:54:57","TransactionReceipt":"LGH3197RIB"},{"B2CChargesPaidAccountAvailableFunds":236543.9,"B2CRecipientIsRegisteredCustomer":"Y","B2CUtilityAccountAvailableFunds":23654.5,"B2CWorkingAccountAvailableFunds":2000,"ReceiverPartyPublicName":"254722000000 - Safaricom PLC","TransactionAmount":8000,"TransactionCompletedDateTime":"17.07.2017 10:54:57","TransactionReceipt":"LGH3197RIB"},{"B2CChargesPaidAccountAvailableFunds":236543.9,"B2CRecipientIsRegisteredCustomer":"Y","B2CUtilityAccountAvailableFunds":23654.5,"B2CWorkingAccountAvailableFunds":2000,"ReceiverPartyPublicName":"254722000000 - Safaricom PLC","TransactionAmount":8000,"TransactionCompletedDateTime":"17.07.2017 10:54:57","TransactionReceipt":"LGH3197RIB"}]}}},"result":{"type":{"type":"string"},"example":"Id inventore."}},"B2CTimeout":{"name":"B2CTimeout","description":"B2C Queue TimeOut URL","payload":{"type":{"$ref":"#/definitions/B2CPaymentResult"},"example":{"ReferenceData":{"ReferenceItem":{"QueueTimeoutURL":"https://internalsandbox.safaricom.co.ke/mpesa/b2cresults/v1/submit"}},"Result":{"ConversationId":"236543-276372-2","OriginatorConversationId":"AG_2376487236_126732989KJHJKH","ResultCode":0,"ResultDesc":"Initiator information is invalid","ResultType":0,"TransactionID":"LHG31AA5TX"},"ResultParameters":{"ResultParameter":[{"B2CChargesPaidAccountAvailableFunds":236543.9,"B2CRecipientIsRegisteredCustomer":"Y","B2CUtilityAccountAvailableFunds":23654.5,"B2CWorkingAccountAvailableFunds":2000,"ReceiverPartyPublicName":"254722000000 - Safaricom PLC","TransactionAmount":8000,"TransactionCompletedDateTime":"17.07.2017 10:54:57","TransactionReceipt":"LGH3197RIB"},{"B2CChargesPaidAccountAvailableFunds":236543.9,"B2CRecipientIsRegisteredCustomer":"Y","B2CUtilityAccountAvailableFunds":23654.5,"B2CWorkingAccountAvailableFunds":2000,"ReceiverPartyPublicName":"254722000000 - Safaricom PLC","TransactionAmount":8000,"TransactionCompletedDateTime":"17.07.2017 10:54:57","TransactionReceipt":"LGH3197RIB"},{"B2CChargesPaidAccountAvailableFunds":236543.9,"B2CRecipientIsRegisteredCustomer":"Y","B2CUtilityAccountAvailableFunds":23654.5,"B2CWorkingAccountAvailableFunds":2000,"ReceiverPartyPublicName":"254722000000 - Safaricom PLC","TransactionAmount":8000,"TransactionCompletedDateTime":"17.07.2017 10:54:57","TransactionReceipt":"LGH3197RIB"},{"B2CChargesPaidAccountAvailableFunds":236543.9,"B2CRecipientIsRegisteredCustomer":"Y","B2CUtilityAccountAvailableFunds":23654.5,"B2CWorkingAccountAvailableFunds":2000,"ReceiverPartyPublicName":"254722000000 - Safaricom PLC","TransactionAmount":8000,"TransactionCompletedDateTime":"17.07.2017 10:54:57","TransactionReceipt":"LGH3197RIB"}]}}},"result":{"type":{"type":"string"},"example":"Quia autem exercitationem earum."}},"C2BConfirmation":{"name":"C2BConfirmation","description":"C2B Confirmation URL","payload":{"type":{"$ref":"#/definitions/ConfirmationResult"},"example":{"BillRefNumber":"jv1","BusinessShortCode":654321,"FirstName":"John","InvoiceNumber":"Aut suscipit qui porro distinctio nisi nesciunt.","LastName":"Jane","MSISDN":5249688152708809860,"MiddleName":"Doe","OrgAccountBalance":30671,"ThirdPartyTransID":"Qui omnis ratione fugiat nostrum fugiat voluptatem.","TransAmount":100,"TransID":"LHG31AA5TX","TransTime":"20180713154301","TransactionType":"Pay Bill"}},"result":{"type":{"type":"string"},"example":"Ullam optio voluptatibus."}},"C2BValidation":{"name":"C2BValidation","description":"C2B Validation URL","payload":{"type":{"$ref":"#/definitions/ValidationResult"},"example":{"BillRefNumber":"iig","BusinessShortCode":654321,"FirstName":"John","InvoiceNumber":"Ut eum vel fuga assumenda.","LastName":"Jane","MSISDN":4512025500490650930,"MiddleName":"Doe","OrgAccountBalance":30671,"ThirdPartyTransID":"Magni sed commodi a ut.","TransAmount":100,"TransID":"LHG31AA5TX","TransTime":"20180713154301","TransactionType":"Buy Goods"}},"result":{"type":{"type":"string"},"example":"Inventore magni."}},"ReversalResult":{"name":"ReversalResult","description":"Reversal Result URL","payload":{"type":{"$ref":"#/definitions/ReversalResult"},"example":{"Result":{"ConversationId":"236543-276372-2","OriginatorConversationId":"AG_2376487236_126732989KJHJKH","ReferenceData":{"ReferenceItem":{"QueueTimeoutURL":"https://internalsandbox.safaricom.co.ke/mpesa/reversalresults/v1/submit"}},"ResultCode":0,"ResultDesc":"Initiator information is invalid","ResultType":0,"TransactionID":"LHG31AA5TX"}}},"result":{"type":{"type":"string"},"example":"Quam illum aut soluta."}},"ReversalTimeout":{"name":"ReversalTimeout","description":"Reversal Queue TimeOut URL","payload":{"type":{"$ref":"#/definitions/ReversalResult"},"example":{"Result":{"ConversationId":"236543-276372-2","OriginatorConversationId":"AG_2376487236_126732989KJHJKH","ReferenceData":{"ReferenceItem":{"QueueTimeoutURL":"https://internalsandbox.safaricom.co.ke/mpesa/reversalresults/v1/submit"}},"ResultCode":0,"ResultDesc":"Initiator information is invalid","ResultType":0,"TransactionID":"LHG31AA5TX"}}},"result":{"type":{"type":"string"},"example":"Recusandae autem deserunt quibusdam."}},"TransactionStatusResult":{"name":"TransactionStatusResult","description":"Transaction Status Result URL","payload":{"type":{"$ref":"#/definitions/TransactionStatusResult"},"example":{"Result":{"ConversationId":"236543-276372-2","OriginatorConversationId":"AG_2376487236_126732989KJHJKH","ReferenceData":{"ReferenceItem":{"Occasion":"Occasion"}},"ResultCode":0,"ResultDesc":"Initiator information is invalid","ResultParameters":{"ResultParameter":[{"Amount":10,"ConversationID":"AG_20170727_00004492b1b6d0078fbe","CreditPartyName":"254708374149 - John Doe","DebitAccountType":"Utility Account","DebitPartyCharges":"Fee For B2C Payment|KES|33.00","DebitPartyName":"600134 - Safaricom157","FinalisedTime":"20170727101415","InitiatedTime":"20170727101415","Originator Conversation ID":"19455-773836-1","ReasonType":"Salary Payment via API","ReceiptNo":"LGR919G2AV","TransactionReason":"Transaction Reason","TransactionStatus":"Completed"},{"Amount":10,"ConversationID":"AG_20170727_00004492b1b6d0078fbe","CreditPartyName":"254708374149 - John Doe","DebitAccountType":"Utility Account","DebitPartyCharges":"Fee For B2C Payment|KES|33.00","DebitPartyName":"600134 - Safaricom157","FinalisedTime":"20170727101415","InitiatedTime":"20170727101415","Originator Conversation ID":"19455-773836-1","ReasonType":"Salary Payment via API","ReceiptNo":"LGR919G2AV","TransactionReason":"Transaction Reason","TransactionStatus":"Completed"},{"Amount":10,"ConversationID":"AG_20170727_00004492b1b6d0078fbe","CreditPartyName":"254708374149 - John Doe","DebitAccountType":"Utility Account","DebitPartyCharges":"Fee For B2C Payment|KES|33.00","DebitPartyName":"600134 - Safaricom157","FinalisedTime":"20170727101415","InitiatedTime":"20170727101415","Originator Conversation ID":"19455-773836-1","ReasonType":"Salary Payment via API","ReceiptNo":"LGR919G2AV","TransactionReason":"Transaction Reason","TransactionStatus":"Completed"}]},"ResultType":0,"TransactionID":"LHG31AA5TX"}}},"result":{"type":{"type":"string"},"example":"Quam omnis autem explicabo non similique ad."}},"TransactionStatusTimeout":{"name":"TransactionStatusTimeout","description":"Transaction Status Queue TimeOut URL","payload":{"type":{"$ref":"#/definitions/TransactionStatusResult"},"example":{"Result":{"ConversationId":"236543-276372-2","OriginatorConversationId":"AG_2376487236_126732989KJHJKH","ReferenceData":{"ReferenceItem":{"Occasion":"Occasion"}},"ResultCode":0,"ResultDesc":"Initiator information is invalid","ResultParameters":{"ResultParameter":[{"Amount":10,"ConversationID":"AG_20170727_00004492b1b6d0078fbe","CreditPartyName":"254708374149 - John Doe","DebitAccountType":"Utility Account","DebitPartyCharges":"Fee For B2C Payment|KES|33.00","DebitPartyName":"600134 - Safaricom157","FinalisedTime":"20170727101415","InitiatedTime":"20170727101415","Originator Conversation ID":"19455-773836-1","ReasonType":"Salary Payment via API","ReceiptNo":"LGR919G2AV","TransactionReason":"Transaction Reason","TransactionStatus":"Completed"},{"Amount":10,"ConversationID":"AG_20170727_00004492b1b6d0078fbe","CreditPartyName":"254708374149 - John Doe","DebitAccountType":"Utility Account","DebitPartyCharges":"Fee For B2C Payment|KES|33.00","DebitPartyName":"600134 - Safaricom157","FinalisedTime":"20170727101415","InitiatedTime":"20170727101415","Originator Conversation ID":"19455-773836-1","ReasonType":"Salary Payment via API","ReceiptNo":"LGR919G2AV","TransactionReason":"Transaction Reason","TransactionStatus":"Completed"},{"Amount":10,"ConversationID":"AG_20170727_00004492b1b6d0078fbe","CreditPartyName":"254708374149 - John Doe","DebitAccountType":"Utility Account","DebitPartyCharges":"Fee For B2C Payment|KES|33.00","DebitPartyName":"600134 - Safaricom157","FinalisedTime":"20170727101415","InitiatedTime":"20170727101415","Originator Conversation ID":"19455-773836-1","ReasonType":"Salary Payment via API","ReceiptNo":"LGR919G2AV","TransactionReason":"Transaction Reason","TransactionStatus":"Completed"}]},"ResultType":0,"TransactionID":"LHG31AA5TX"}}},"result":{"type":{"type":"string"},"example":"Blanditiis eum excepturi."}}}},"swagger":{"name":"swagger","description":"The swagger service serves the API swagger definition."}},"definitions":{"AccountBalanceParameters":{"title":"AccountBalanceParameters","type":"object","properties":{"AccountBalance":{"type":"string","example":"Working Account|KES|46713.00|46713.00|0.00|0.00\u0026Float Account|KES|0.00|0.00|0.00|0.00\u0026Utility Account|KES|49217.00|49217.00|0.00|0.00\u0026Charges Paid Account|KES|-220.00|-220.00|0.00|0.00\u0026Organization Settlement Account|KES|0.00|0.00|0.00|0.00"},"BOCompletedTime":{"type":"string","example":"20170728095642","format":"date-time"}},"example":{"AccountBalance":"Working Account|KES|46713.00|46713.00|0.00|0.00\u0026Float Account|KES|0.00|0.00|0.00|0.00\u0026Utility Account|KES|49217.00|49217.00|0.00|0.00\u0026Charges Paid Account|KES|-220.00|-220.00|0.00|0.00\u0026Organization Settlement Account|KES|0.00|0.00|0.00|0.00","BOCompletedTime":"20170728095642"}},"AccountBalanceParametersRequestBody":{"title":"AccountBalanceParametersRequestBody","type":"object","properties":{"AccountBalance":{"type":"string","example":"Working Account|KES|46713.00|46713.00|0.00|0.00\u0026Float Account|KES|0.00|0.00|0.00|0.00\u0026Utility Account|KES|49217.00|49217.00|0.00|0.00\u0026Charges Paid Account|KES|-220.00|-220.00|0.00|0.00\u0026Organization Settlement Account|KES|0.00|0.00|0.00|0.00"},"BOCompletedTime":{"type":"string","example":"20170728095642","format":"date-time"}},"example":{"AccountBalance":"Working Account|KES|46713.00|46713.00|0.00|0.00\u0026Float Account|KES|0.00|0.00|0.00|0.00\u0026Utility Account|KES|49217.00|49217.00|0.00|0.00\u0026Charges Paid Account|KES|-220.00|-220.00|0.00|0.00\u0026Organization Settlement Account|KES|0.00|0.00|0.00|0.00","BOCompletedTime":"20170728095642"}},"AccountBalanceResult":{"title":"AccountBalanceResult","type":"object","properties":{"Result":{"type":"object","properties":{"ConversationId":{"type":"string","description":"Unique identifier for the transaction request.","example":"236543-276372-2"},"OriginatorConversationId":{"type":"string","description":"Unique identifier for the transaction request.","example":"AG_2376487236_126732989KJHJKH"},"ReferenceData":{"type":"object","properties":{"ReferenceItem":{"type":"object","example":{"QueueTimeoutURL":"https://internalsandbox.safaricom.co.ke/mpesa/abresults/v1/submit"},"additionalProperties":true}},"example":{"ReferenceItem":{"QueueTimeoutURL":"https://internalsandbox.safaricom.co.ke/mpesa/abresults/v1/submit"}}},"ResultCode":{"type":"integer","description":"Numeric status code indicating the status of the transaction processing","example":0,"format":"int64"},"ResultDesc":{"type":"string","description":"Message from the API that gives the status of the request","example":"Initiator information is invalid"},"ResultParameters":{"type":"object","properties":{"ResultParameter":{"type":"array","items":{"$ref":"#/definitions/AccountBalanceParameters"},"example":[{"AccountBalance":"Working Account|KES|46713.00|46713.00|0.00|0.00\u0026Float Account|KES|0.00|0.00|0.00|0.00\u0026Utility Account|KES|49217.00|49217.00|0.00|0.00\u0026Charges Paid Account|KES|-220.00|-220.00|0.00|0.00\u0026Organization Settlement Account|KES|0.00|0.00|0.00|0.00","BOCompletedTime":"20170728095642"},{"AccountBalance":"Working Account|KES|46713.00|46713.00|0.00|0.00\u0026Float Account|KES|0.00|0.00|0.00|0.00\u0026Utility Account|KES|49217.00|49217.00|0.00|0.00\u0026Charges Paid Account|KES|-220.00|-220.00|0.00|0.00\u0026Organization Settlement Account|KES|0.00|0.00|0.00|0.00","BOCompletedTime":"20170728095642"},{"AccountBalance":"Working Account|KES|46713.00|46713.00|0.00|0.00\u0026Float Account|KES|0.00|0.00|0.00|0.00\u0026Utility Account|KES|49217.00|49217.00|0.00|0.00\u0026Charges Paid Account|KES|-220.00|-220.00|0.00|0.00\u0026Organization Settlement Account|KES|0.00|0.00|0.00|0.00","BOCompletedTime":"20170728095642"}]}},"example":{"ResultParameter":[{"AccountBalance":"Working Account|KES|46713.00|46713.00|0.00|0.00\u0026Float Account|KES|0.00|0.00|0.00|0.00\u0026Utility Account|KES|49217.00|49217.00|0.00|0.00\u0026Charges Paid Account|KES|-220.00|-220.00|0.00|0.00\u0026Organization Settlement Account|KES|0.00|0.00|0.00|0.00","BOCompletedTime":"20170728095642"},{"AccountBalance":"Working Account|KES|46713.00|46713.00|0.00|0.00\u0026Float Account|KES|0.00|0.00|0.00|0.00\u0026Utility Account|KES|49217.00|49217.00|0.00|0.00\u0026Charges Paid Account|KES|-220.00|-220.00|0.00|0.00\u0026Organization Settlement Account|KES|0.00|0.00|0.00|0.00","BOCompletedTime":"20170728095642"},{"AccountBalance":"Working Account|KES|46713.00|46713.00|0.00|0.00\u0026Float Account|KES|0.00|0.00|0.00|0.00\u0026Utility Account|KES|49217.00|49217.00|0.00|0.00\u0026Charges Paid Account|KES|-220.00|-220.00|0.00|0.00\u0026Organization Settlement Account|KES|0.00|0.00|0.00|0.00","BOCompletedTime":"20170728095642"}]}},"ResultType":{"type":"integer","description":"Status code indicating whether transaction was already sent to your listener","default":0,"example":0,"format":"int64"},"TransactionID":{"type":"string","description":"Unique M-PESA transaction ID for every payment request.","example":"LHG31AA5TX"}},"example":{"ConversationId":"236543-276372-2","OriginatorConversationId":"AG_2376487236_126732989KJHJKH","ReferenceData":{"ReferenceItem":{"QueueTimeoutURL":"https://internalsandbox.safaricom.co.ke/mpesa/abresults/v1/submit"}},"ResultCode":0,"ResultDesc":"Initiator information is invalid","ResultParameters":{"ResultParameter":[{"AccountBalance":"Working Account|KES|46713.00|46713.00|0.00|0.00\u0026Float Account|KES|0.00|0.00|0.00|0.00\u0026Utility Account|KES|49217.00|49217.00|0.00|0.00\u0026Charges Paid Account|KES|-220.00|-220.00|0.00|0.00\u0026Organization Settlement Account|KES|0.00|0.00|0.00|0.00","BOCompletedTime":"20170728095642"},{"AccountBalance":"Working Account|KES|46713.00|46713.00|0.00|0.00\u0026Float Account|KES|0.00|0.00|0.00|0.00\u0026Utility Account|KES|49217.00|49217.00|0.00|0.00\u0026Charges Paid Account|KES|-220.00|-220.00|0.00|0.00\u0026Organization Settlement Account|KES|0.00|0.00|0.00|0.00","BOCompletedTime":"20170728095642"},{"AccountBalance":"Working Account|KES|46713.00|46713.00|0.00|0.00\u0026Float Account|KES|0.00|0.00|0.00|0.00\u0026Utility Account|KES|49217.00|49217.00|0.00|0.00\u0026Charges Paid Account|KES|-220.00|-220.00|0.00|0.00\u0026Organization Settlement Account|KES|0.00|0.00|0.00|0.00","BOCompletedTime":"20170728095642"}]},"ResultType":0,"TransactionID":"LHG31AA5TX"}}},"example":{"Result":{"ConversationId":"236543-276372-2","OriginatorConversationId":"AG_2376487236_126732989KJHJKH","ReferenceData":{"ReferenceItem":{"QueueTimeoutURL":"https://internalsandbox.safaricom.co.ke/mpesa/abresults/v1/submit"}},"ResultCode":0,"ResultDesc":"Initiator information is invalid","ResultParameters":{"ResultParameter":[{"AccountBalance":"Working Account|KES|46713.00|46713.00|0.00|0.00\u0026Float Account|KES|0.00|0.00|0.00|0.00\u0026Utility Account|KES|49217.00|49217.00|0.00|0.00\u0026Charges Paid Account|KES|-220.00|-220.00|0.00|0.00\u0026Organization Settlement Account|KES|0.00|0.00|0.00|0.00","BOCompletedTime":"20170728095642"},{"AccountBalance":"Working Account|KES|46713.00|46713.00|0.00|0.00\u0026Float Account|KES|0.00|0.00|0.00|0.00\u0026Utility Account|KES|49217.00|49217.00|0.00|0.00\u0026Charges Paid Account|KES|-220.00|-220.00|0.00|0.00\u0026Organization Settlement Account|KES|0.00|0.00|0.00|0.00","BOCompletedTime":"20170728095642"},{"AccountBalance":"Working Account|KES|46713.00|46713.00|0.00|0.00\u0026Float Account|KES|0.00|0.00|0.00|0.00\u0026Utility Account|KES|49217.00|49217.00|0.00|0.00\u0026Charges Paid Account|KES|-220.00|-220.00|0.00|0.00\u0026Organization Settlement Account|KES|0.00|0.00|0.00|0.00","BOCompletedTime":"20170728095642"}]},"ResultType":0,"TransactionID":"LHG31AA5TX"}}},"B2CPaymentResult":{"title":"B2CPaymentResult","type":"object","properties":{"ReferenceData":{"type":"object","properties":{"ReferenceItem":{"type":"object","example":{"QueueTimeoutURL":"https://internalsandbox.safaricom.co.ke/mpesa/b2cresults/v1/submit"},"additionalProperties":true}},"example":{"ReferenceItem":{"QueueTimeoutURL":"https://internalsandbox.safaricom.co.ke/mpesa/b2cresults/v1/submit"}}},"Result":{"type":"object","properties":{"ConversationId":{"type":"string","description":"Unique identifier for the transaction request.","example":"236543-276372-2"},"OriginatorConversationId":{"type":"string","description":"Unique identifier for the transaction request.","example":"AG_2376487236_126732989KJHJKH"},"ResultCode":{"type":"integer","description":"Numeric status code indicating the status of the transaction processing","example":0,"format":"int64"},"ResultDesc":{"type":"string","description":"Message from the API that gives the status of the request","example":"Initiator information is invalid"},"ResultType":{"type":"integer","description":"Status code indicating whether transaction was already sent to your listener","default":0,"example":0,"format":"int64"},"TransactionID":{"type":"string","description":"Unique M-PESA transaction ID for every payment request.","example":"LHG31AA5TX"}},"example":{"ConversationId":"236543-276372-2","OriginatorConversationId":"AG_2376487236_126732989KJHJKH","ResultCode":0,"ResultDesc":"Initiator information is invalid","ResultType":0,"TransactionID":"LHG31AA5TX"}},"ResultParameters":{"type":"object","properties":{"ResultParameter":{"type":"array","items":{"$ref":"#/definitions/B2CResultParameters"},"example":[{"B2CChargesPaidAccountAvailableFunds":236543.9,"B2CRecipientIsRegisteredCustomer":"Y","B2CUtilityAccountAvailableFunds":23654.5,"B2CWorkingAccountAvailableFunds":2000,"ReceiverPartyPublicName":"254722000000 - Safaricom PLC","TransactionAmount":8000,"TransactionCompletedDateTime":"17.07.2017 10:54:57","TransactionReceipt":"LGH3197RIB"},{"B2CChargesPaidAccountAvailableFunds":236543.9,"B2CRecipientIsRegisteredCustomer":"Y","B2CUtilityAccountAvailableFunds":23654.5,"B2CWorkingAccountAvailableFunds":2000,"ReceiverPartyPublicName":"254722000000 - Safaricom PLC","TransactionAmount":8000,"TransactionCompletedDateTime":"17.07.2017 10:54:57","TransactionReceipt":"LGH3197RIB"}]}},"example":{"ResultParameter":[{"B2CChargesPaidAccountAvailableFunds":236543.9,"B2CRecipientIsRegisteredCustomer":"Y","B2CUtilityAccountAvailableFunds":23654.5,"B2CWorkingAccountAvailableFunds":2000,"ReceiverPartyPublicName":"254722000000 - Safaricom PLC","TransactionAmount":8000,"TransactionCompletedDateTime":"17.07.2017 10:54:57","TransactionReceipt":"LGH3197RIB"},{"B2CChargesPaidAccountAvailableFunds":236543.9,"B2CRecipientIsRegisteredCustomer":"Y","B2CUtilityAccountAvailableFunds":23654.5,"B2CWorkingAccountAvailableFunds":2000,"ReceiverPartyPublicName":"254722000000 - Safaricom PLC","TransactionAmount":8000,"TransactionCompletedDateTime":"17.07.2017 10:54:57","TransactionReceipt":"LGH3197RIB"},{"B2CChargesPaidAccountAvailableFunds":236543.9,"B2CRecipientIsRegisteredCustomer":"Y","B2CUtilityAccountAvailableFunds":23654.5,"B2CWorkingAccountAvailableFunds":2000,"ReceiverPartyPublicName":"254722000000 - Safaricom PLC","TransactionAmount":8000,"TransactionCompletedDateTime":"17.07.2017 10:54:57","TransactionReceipt":"LGH3197RIB"}]}}},"description":"Result Parameters","example":{"ReferenceData":{"ReferenceItem":{"QueueTimeoutURL":"https://internalsandbox.safaricom.co.ke/mpesa/b2cresults/v1/submit"}},"Result":{"ConversationId":"236543-276372-2","OriginatorConversationId":"AG_2376487236_126732989KJHJKH","ResultCode":0,"ResultDesc":"Initiator information is invalid","ResultType":0,"TransactionID":"LHG31AA5TX"},"ResultParameters":{"ResultParameter":[{"B2CChargesPaidAccountAvailableFunds":236543.9,"B2CRecipientIsRegisteredCustomer":"Y","B2CUtilityAccountAvailableFunds":23654.5,"B2CWorkingAccountAvailableFunds":2000,"ReceiverPartyPublicName":"254722000000 - Safaricom PLC","TransactionAmount":8000,"TransactionCompletedDateTime":"17.07.2017 10:54:57","TransactionReceipt":"LGH3197RIB"},{"B2CChargesPaidAccountAvailableFunds":236543.9,"B2CRecipientIsRegisteredCustomer":"Y","B2CUtilityAccountAvailableFunds":23654.5,"B2CWorkingAccountAvailableFunds":2000,"ReceiverPartyPublicName":"254722000000 - Safaricom PLC","TransactionAmount":8000,"TransactionCompletedDateTime":"17.07.2017 10:54:57","TransactionReceipt":"LGH3197RIB"},{"B2CChargesPaidAccountAvailableFunds":236543.9,"B2CRecipientIsRegisteredCustomer":"Y","B2CUtilityAccountAvailableFunds":23654.5,"B2CWorkingAccountAvailableFunds":2000,"ReceiverPartyPublicName":"254722000000 - Safaricom PLC","TransactionAmount":8000,"TransactionCompletedDateTime":"17.07.2017 10:54:57","TransactionReceipt":"LGH3197RIB"}]}}},"B2CResultParameters":{"title":"B2CResultParameters","type":"object","properties":{"B2CChargesPaidAccountAvailableFunds":{"type":"number","description":"Available balance of the Charges Paid account under the B2C shortcode used in the transaction.","example":236543.9,"format":"double"},"B2CRecipientIsRegisteredCustomer":{"type":"string","description":"Key indicating whether customer is registered on M-PESA","example":"Y","enum":["Y","N"],"pattern":"[a-zA-Z]+"},"B2CUtilityAccountAvailableFunds":{"type":"number","description":"Available balance of the Utility account under the B2C shortcode used in the transaction.","example":23654.5,"format":"double"},"B2CWorkingAccountAvailableFunds":{"type":"number","description":"Available balance of the Working account under the B2C shortcode used in the transaction.","example":2000,"format":"double"},"ReceiverPartyPublicName":{"type":"string","description":"This is the name and phone number of the customer who received the payment.","example":"254722000000 - Safaricom PLC","pattern":"[a-zA-Z]+"},"TransactionAmount":{"type":"integer","description":"This is the amount that was transacted.","example":8000,"format":"int64"},"TransactionCompletedDateTime":{"type":"string","description":"This is the date and time that the transaction completed M-PESA.","example":"17.07.2017 10:54:57","format":"date-time"},"TransactionReceipt":{"type":"string","description":"This is a unique M-PESA transaction ID for every payment request.","example":"LGH3197RIB","pattern":"[a-zA-Z]+"}},"example":{"B2CChargesPaidAccountAvailableFunds":236543.9,"B2CRecipientIsRegisteredCustomer":"Y","B2CUtilityAccountAvailableFunds":23654.5,"B2CWorkingAccountAvailableFunds":2000,"ReceiverPartyPublicName":"254722000000 - Safaricom PLC","TransactionAmount":8000,"TransactionCompletedDateTime":"17.07.2017 10:54:57","TransactionReceipt":"LGH3197RIB"}},"B2CResultParametersRequestBody":{"title":"B2CResultParametersRequestBody","type":"object","properties":{"B2CChargesPaidAccountAvailableFunds":{"type":"number","description":"Available balance of the Charges Paid account under the B2C shortcode used in the transaction.","example":236543.9,"format":"double"},"B2CRecipientIsRegisteredCustomer":{"type":"string","description":"Key indicating whether customer is registered on M-PESA","example":"Y","enum":["Y","N"],"pattern":"[a-zA-Z]+"},"B2CUtilityAccountAvailableFunds":{"type":"number","description":"Available balance of the Utility account under the B2C shortcode used in the transaction.","example":23654.5,"format":"double"},"B2CWorkingAccountAvailableFunds":{"type":"number","description":"Available balance of the Working account under the B2C shortcode used in the transaction.","example":2000,"format":"double"},"ReceiverPartyPublicName":{"type":"string","description":"This is the name and phone number of the customer who received the payment.","example":"254722000000 - Safaricom PLC","pattern":"[a-zA-Z]+"},"TransactionAmount":{"type":"integer","description":"This is the amount that was transacted.","example":8000,"format":"int64"},"TransactionCompletedDateTime":{"type":"string","description":"This is the date and time that the transaction completed M-PESA.","example":"17.07.2017 10:54:57","format":"date-time"},"TransactionReceipt":{"type":"string","description":"This is a unique M-PESA transaction ID for every payment request.","example":"LGH3197RIB","pattern":"[a-zA-Z]+"}},"example":{"B2CChargesPaidAccountAvailableFunds":236543.9,"B2CRecipientIsRegisteredCustomer":"Y","B2CUtilityAccountAvailableFunds":23654.5,"B2CWorkingAccountAvailableFunds":2000,"ReceiverPartyPublicName":"254722000000 - Safaricom PLC","TransactionAmount":8000,"TransactionCompletedDateTime":"17.07.2017 10:54:57","TransactionReceipt":"LGH3197RIB"}},"ConfirmationResult":{"title":"ConfirmationResult","type":"object","properties":{"BillRefNumber":{"type":"string","description":"Account number for which the customer is making the payment","example":"wl2","maxLength":20},"BusinessShortCode":{"type":"integer","description":"Organizations shortcode (Paybill or Buygoods)","example":654321,"format":"int64"},"FirstName":{"type":"string","description":"First Name of the customer making the payment.","example":"John"},"InvoiceNumber":{"type":"string","example":"Fugiat delectus eos eum et fugiat."},"LastName":{"type":"string","description":"Last Name of the customer making payment.","example":"Jane"},"MSISDN":{"type":"integer","description":"Mobile number of the customer making the payment.","example":4250186694084355984,"format":"int64"},"MiddleName":{"type":"string","description":"Middle Name of the customer making the payment.","example":"Doe"},"OrgAccountBalance":{"type":"integer","description":"Current utility account balance of the payment receiving organization shortcode","example":30671,"format":"int64"},"ThirdPartyTransID":{"type":"string","example":"Voluptatem voluptatibus alias nemo."},"TransAmount":{"type":"integer","description":"The Amount transacted normally a numeric value","example":100,"format":"int64"},"TransID":{"type":"string","description":"Unique M-Pesa transaction ID for every payment request","example":"LHG31AA5TX"},"TransTime":{"type":"string","description":"Timestamp of the transaction","example":"20180713154301","format":"date-time"},"TransactionType":{"type":"string","description":"Transaction type specified during the payment request.","example":"Buy Goods","enum":["Buy Goods","Pay Bill"]}},"example":{"BillRefNumber":"tp2","BusinessShortCode":654321,"FirstName":"John","InvoiceNumber":"Omnis quia optio fugit.","LastName":"Jane","MSISDN":524695063826075251,"MiddleName":"Doe","OrgAccountBalance":30671,"ThirdPartyTransID":"Enim voluptatem.","TransAmount":100,"TransID":"LHG31AA5TX","TransTime":"20180713154301","TransactionType":"Buy Goods"}},"Empty":{"title":"Empty","type":"object","description":"Empty represents empty values","example":{}},"MpesaAccountBalanceResultRequestBody":{"title":"MpesaAccountBalanceResultRequestBody","type":"object","properties":{"Result":{"type":"object","properties":{"ConversationId":{"type":"string","description":"Unique identifier for the transaction request.","example":"236543-276372-2"},"OriginatorConversationId":{"type":"string","description":"Unique identifier for the transaction request.","example":"AG_2376487236_126732989KJHJKH"},"ReferenceData":{"type":"object","properties":{"ReferenceItem":{"type":"object","example":{"QueueTimeoutURL":"https://internalsandbox.safaricom.co.ke/mpesa/abresults/v1/submit"},"additionalProperties":true}},"example":{"ReferenceItem":{"QueueTimeoutURL":"https://internalsandbox.safaricom.co.ke/mpesa/abresults/v1/submit"}}},"ResultCode":{"type":"integer","description":"Numeric status code indicating the status of the transaction processing","example":0,"format":"int64"},"ResultDesc":{"type":"string","description":"Message from the API that gives the status of the request","example":"Initiator information is invalid"},"ResultParameters":{"type":"object","properties":{"ResultParameter":{"type":"array","items":{"$ref":"#/definitions/AccountBalanceParametersRequestBody"},"example":[{"AccountBalance":"Working Account|KES|46713.00|46713.00|0.00|0.00\u0026Float Account|KES|0.00|0.00|0.00|0.00\u0026Utility Account|KES|49217.00|49217.00|0.00|0.00\u0026Charges Paid Account|KES|-220.00|-220.00|0.00|0.00\u0026Organization Settlement Account|KES|0.00|0.00|0.00|0.00","BOCompletedTime":"20170728095642"},{"AccountBalance":"Working Account|KES|46713.00|46713.00|0.00|0.00\u0026Float Account|KES|0.00|0.00|0.00|0.00\u0026Utility Account|KES|49217.00|49217.00|0.00|0.00\u0026Charges Paid Account|KES|-220.00|-220.00|0.00|0.00\u0026Organization Settlement Account|KES|0.00|0.00|0.00|0.00","BOCompletedTime":"20170728095642"}]}},"example":{"ResultParameter":[{"AccountBalance":"Working Account|KES|46713.00|46713.00|0.00|0.00\u0026Float Account|KES|0.00|0.00|0.00|0.00\u0026Utility Account|KES|49217.00|49217.00|0.00|0.00\u0026Charges Paid Account|KES|-220.00|-220.00|0.00|0.00\u0026Organization Settlement Account|KES|0.00|0.00|0.00|0.00","BOCompletedTime":"20170728095642"},{"AccountBalance":"Working Account|KES|46713.00|46713.00|0.00|0.00\u0026Float Account|KES|0.00|0.00|0.00|0.00\u0026Utility Account|KES|49217.00|49217.00|0.00|0.00\u0026Charges Paid Account|KES|-220.00|-220.00|0.00|0.00\u0026Organization Settlement Account|KES|0.00|0.00|0.00|0.00","BOCompletedTime":"20170728095642"},{"AccountBalance":"Working Account|KES|46713.00|46713.00|0.00|0.00\u0026Float Account|KES|0.00|0.00|0.00|0.00\u0026Utility Account|KES|49217.00|49217.00|0.00|0.00\u0026Charges Paid Account|KES|-220.00|-220.00|0.00|0.00\u0026Organization Settlement Account|KES|0.00|0.00|0.00|0.00","BOCompletedTime":"20170728095642"},{"AccountBalance":"Working Account|KES|46713.00|46713.00|0.00|0.00\u0026Float Account|KES|0.00|0.00|0.00|0.00\u0026Utility Account|KES|49217.00|49217.00|0.00|0.00\u0026Charges Paid Account|KES|-220.00|-220.00|0.00|0.00\u0026Organization Settlement Account|KES|0.00|0.00|0.00|0.00","BOCompletedTime":"20170728095642"}]}},"ResultType":{"type":"integer","description":"Status code indicating whether transaction was already sent to your listener","default":0,"example":0,"format":"int64"},"TransactionID":{"type":"string","description":"Unique M-PESA transaction ID for every payment request.","example":"LHG31AA5TX"}},"example":{"ConversationId":"236543-276372-2","OriginatorConversationId":"AG_2376487236_126732989KJHJKH","ReferenceData":{"ReferenceItem":{"QueueTimeoutURL":"https://internalsandbox.safaricom.co.ke/mpesa/abresults/v1/submit"}},"ResultCode":0,"ResultDesc":"Initiator information is invalid","ResultParameters":{"ResultParameter":[{"AccountBalance":"Working Account|KES|46713.00|46713.00|0.00|0.00\u0026Float Account|KES|0.00|0.00|0.00|0.00\u0026Utility Account|KES|49217.00|49217.00|0.00|0.00\u0026Charges Paid Account|KES|-220.00|-220.00|0.00|0.00\u0026Organization Settlement Account|KES|0.00|0.00|0.00|0.00","BOCompletedTime":"20170728095642"},{"AccountBalance":"Working Account|KES|46713.00|46713.00|0.00|0.00\u0026Float Account|KES|0.00|0.00|0.00|0.00\u0026Utility Account|KES|49217.00|49217.00|0.00|0.00\u0026Charges Paid Account|KES|-220.00|-220.00|0.00|0.00\u0026Organization Settlement Account|KES|0.00|0.00|0.00|0.00","BOCompletedTime":"20170728095642"},{"AccountBalance":"Working Account|KES|46713.00|46713.00|0.00|0.00\u0026Float Account|KES|0.00|0.00|0.00|0.00\u0026Utility Account|KES|49217.00|49217.00|0.00|0.00\u0026Charges Paid Account|KES|-220.00|-220.00|0.00|0.00\u0026Organization Settlement Account|KES|0.00|0.00|0.00|0.00","BOCompletedTime":"20170728095642"},{"AccountBalance":"Working Account|KES|46713.00|46713.00|0.00|0.00\u0026Float Account|KES|0.00|0.00|0.00|0.00\u0026Utility Account|KES|49217.00|49217.00|0.00|0.00\u0026Charges Paid Account|KES|-220.00|-220.00|0.00|0.00\u0026Organization Settlement Account|KES|0.00|0.00|0.00|0.00","BOCompletedTime":"20170728095642"}]},"ResultType":0,"TransactionID":"LHG31AA5TX"}}},"example":{"Result":{"ConversationId":"236543-276372-2","OriginatorConversationId":"AG_2376487236_126732989KJHJKH","ReferenceData":{"ReferenceItem":{"QueueTimeoutURL":"https://internalsandbox.safaricom.co.ke/mpesa/abresults/v1/submit"}},"ResultCode":0,"ResultDesc":"Initiator information is invalid","ResultParameters":{"ResultParameter":[{"AccountBalance":"Working Account|KES|46713.00|46713.00|0.00|0.00\u0026Float Account|KES|0.00|0.00|0.00|0.00\u0026Utility Account|KES|49217.00|49217.00|0.00|0.00\u0026Charges Paid Account|KES|-220.00|-220.00|0.00|0.00\u0026Organization Settlement Account|KES|0.00|0.00|0.00|0.00","BOCompletedTime":"20170728095642"},{"AccountBalance":"Working Account|KES|46713.00|46713.00|0.00|0.00\u0026Float Account|KES|0.00|0.00|0.00|0.00\u0026Utility Account|KES|49217.00|49217.00|0.00|0.00\u0026Charges Paid Account|KES|-220.00|-220.00|0.00|0.00\u0026Organization Settlement Account|KES|0.00|0.00|0.00|0.00","BOCompletedTime":"20170728095642"},{"AccountBalance":"Working Account|KES|46713.00|46713.00|0.00|0.00\u0026Float Account|KES|0.00|0.00|0.00|0.00\u0026Utility Account|KES|49217.00|49217.00|0.00|0.00\u0026Charges Paid Account|KES|-220.00|-220.00|0.00|0.00\u0026Organization Settlement Account|KES|0.00|0.00|0.00|0.00","BOCompletedTime":"20170728095642"}]},"ResultType":0,"TransactionID":"LHG31AA5TX"}}},"MpesaAccountBalanceTimeoutRequestBody":{"title":"MpesaAccountBalanceTimeoutRequestBody","type":"object","properties":{"Result":{"type":"object","properties":{"ConversationId":{"type":"string","description":"Unique identifier for the transaction request.","example":"236543-276372-2"},"OriginatorConversationId":{"type":"string","description":"Unique identifier for the transaction request.","example":"AG_2376487236_126732989KJHJKH"},"ReferenceData":{"type":"object","properties":{"ReferenceItem":{"type":"object","example":{"QueueTimeoutURL":"https://internalsandbox.safaricom.co.ke/mpesa/abresults/v1/submit"},"additionalProperties":true}},"example":{"ReferenceItem":{"QueueTimeoutURL":"https://internalsandbox.safaricom.co.ke/mpesa/abresults/v1/submit"}}},"ResultCode":{"type":"integer","description":"Numeric status code indicating the status of the transaction processing","example":0,"format":"int64"},"ResultDesc":{"type":"string","description":"Message from the API that gives the status of the request","example":"Initiator information is invalid"},"ResultParameters":{"type":"object","properties":{"ResultParameter":{"type":"array","items":{"$ref":"#/definitions/AccountBalanceParametersRequestBody"},"example":[{"AccountBalance":"Working Account|KES|46713.00|46713.00|0.00|0.00\u0026Float Account|KES|0.00|0.00|0.00|0.00\u0026Utility Account|KES|49217.00|49217.00|0.00|0.00\u0026Charges Paid Account|KES|-220.00|-220.00|0.00|0.00\u0026Organization Settlement Account|KES|0.00|0.00|0.00|0.00","BOCompletedTime":"20170728095642"},{"AccountBalance":"Working Account|KES|46713.00|46713.00|0.00|0.00\u0026Float Account|KES|0.00|0.00|0.00|0.00\u0026Utility Account|KES|49217.00|49217.00|0.00|0.00\u0026Charges Paid Account|KES|-220.00|-220.00|0.00|0.00\u0026Organization Settlement Account|KES|0.00|0.00|0.00|0.00","BOCompletedTime":"20170728095642"},{"AccountBalance":"Working Account|KES|46713.00|46713.00|0.00|0.00\u0026Float Account|KES|0.00|0.00|0.00|0.00\u0026Utility Account|KES|49217.00|49217.00|0.00|0.00\u0026Charges Paid Account|KES|-220.00|-220.00|0.00|0.00\u0026Organization Settlement Account|KES|0.00|0.00|0.00|0.00","BOCompletedTime":"20170728095642"},{"AccountBalance":"Working Account|KES|46713.00|46713.00|0.00|0.00\u0026Float Account|KES|0.00|0.00|0.00|0.00\u0026Utility Account|KES|49217.00|49217.00|0.00|0.00\u0026Charges Paid Account|KES|-220.00|-220.00|0.00|0.00\u0026Organization Settlement Account|KES|0.00|0.00|0.00|0.00","BOCompletedTime":"20170728095642"}]}},"example":{"ResultParameter":[{"AccountBalance":"Working Account|KES|46713.00|46713.00|0.00|0.00\u0026Float Account|KES|0.00|0.00|0.00|0.00\u0026Utility Account|KES|49217.00|49217.00|0.00|0.00\u0026Charges Paid Account|KES|-220.00|-220.00|0.00|0.00\u0026Organization Settlement Account|KES|0.00|0.00|0.00|0.00","BOCompletedTime":"20170728095642"},{"AccountBalance":"Working Account|KES|46713.00|46713.00|0.00|0.00\u0026Float Account|KES|0.00|0.00|0.00|0.00\u0026Utility Account|KES|49217.00|49217.00|0.00|0.00\u0026Charges Paid Account|KES|-220.00|-220.00|0.00|0.00\u0026Organization Settlement Account|KES|0.00|0.00|0.00|0.00","BOCompletedTime":"20170728095642"}]}},"ResultType":{"type":"integer","description":"Status code indicating whether transaction was already sent to your listener","default":0,"example":0,"format":"int64"},"TransactionID":{"type":"string","description":"Unique M-PESA transaction ID for every payment request.","example":"LHG31AA5TX"}},"example":{"ConversationId":"236543-276372-2","OriginatorConversationId":"AG_2376487236_126732989KJHJKH","ReferenceData":{"ReferenceItem":{"QueueTimeoutURL":"https://internalsandbox.safaricom.co.ke/mpesa/abresults/v1/submit"}},"ResultCode":0,"ResultDesc":"Initiator information is invalid","ResultParameters":{"ResultParameter":[{"AccountBalance":"Working Account|KES|46713.00|46713.00|0.00|0.00\u0026Float Account|KES|0.00|0.00|0.00|0.00\u0026Utility Account|KES|49217.00|49217.00|0.00|0.00\u0026Charges Paid Account|KES|-220.00|-220.00|0.00|0.00\u0026Organization Settlement Account|KES|0.00|0.00|0.00|0.00","BOCompletedTime":"20170728095642"},{"AccountBalance":"Working Account|KES|46713.00|46713.00|0.00|0.00\u0026Float Account|KES|0.00|0.00|0.00|0.00\u0026Utility Account|KES|49217.00|49217.00|0.00|0.00\u0026Charges Paid Account|KES|-220.00|-220.00|0.00|0.00\u0026Organization Settlement Account|KES|0.00|0.00|0.00|0.00","BOCompletedTime":"20170728095642"},{"AccountBalance":"Working Account|KES|46713.00|46713.00|0.00|0.00\u0026Float Account|KES|0.00|0.00|0.00|0.00\u0026Utility Account|KES|49217.00|49217.00|0.00|0.00\u0026Charges Paid Account|KES|-220.00|-220.00|0.00|0.00\u0026Organization Settlement Account|KES|0.00|0.00|0.00|0.00","BOCompletedTime":"20170728095642"},{"AccountBalance":"Working Account|KES|46713.00|46713.00|0.00|0.00\u0026Float Account|KES|0.00|0.00|0.00|0.00\u0026Utility Account|KES|49217.00|49217.00|0.00|0.00\u0026Charges Paid Account|KES|-220.00|-220.00|0.00|0.00\u0026Organization Settlement Account|KES|0.00|0.00|0.00|0.00","BOCompletedTime":"20170728095642"}]},"ResultType":0,"TransactionID":"LHG31AA5TX"}}},"example":{"Result":{"ConversationId":"236543-276372-2","OriginatorConversationId":"AG_2376487236_126732989KJHJKH","ReferenceData":{"ReferenceItem":{"QueueTimeoutURL":"https://internalsandbox.safaricom.co.ke/mpesa/abresults/v1/submit"}},"ResultCode":0,"ResultDesc":"Initiator information is invalid","ResultParameters":{"ResultParameter":[{"AccountBalance":"Working Account|KES|46713.00|46713.00|0.00|0.00\u0026Float Account|KES|0.00|0.00|0.00|0.00\u0026Utility Account|KES|49217.00|49217.00|0.00|0.00\u0026Charges Paid Account|KES|-220.00|-220.00|0.00|0.00\u0026Organization Settlement Account|KES|0.00|0.00|0.00|0.00","BOCompletedTime":"20170728095642"},{"AccountBalance":"Working Account|KES|46713.00|46713.00|0.00|0.00\u0026Float Account|KES|0.00|0.00|0.00|0.00\u0026Utility Account|KES|49217.00|49217.00|0.00|0.00\u0026Charges Paid Account|KES|-220.00|-220.00|0.00|0.00\u0026Organization Settlement Account|KES|0.00|0.00|0.00|0.00","BOCompletedTime":"20170728095642"},{"AccountBalance":"Working Account|KES|46713.00|46713.00|0.00|0.00\u0026Float Account|KES|0.00|0.00|0.00|0.00\u0026Utility Account|KES|49217.00|49217.00|0.00|0.00\u0026Charges Paid Account|KES|-220.00|-220.00|0.00|0.00\u0026Organization Settlement Account|KES|0.00|0.00|0.00|0.00","BOCompletedTime":"20170728095642"},{"AccountBalance":"Working Account|KES|46713.00|46713.00|0.00|0.00\u0026Float Account|KES|0.00|0.00|0.00|0.00\u0026Utility Account|KES|49217.00|49217.00|0.00|0.00\u0026Charges Paid Account|KES|-220.00|-220.00|0.00|0.00\u0026Organization Settlement Account|KES|0.00|0.00|0.00|0.00","BOCompletedTime":"20170728095642"}]},"ResultType":0,"TransactionID":"LHG31AA5TX"}}},"MpesaB2CResultRequestBody":{"title":"MpesaB2CResultRequestBody","type":"object","properties":{"ReferenceData":{"type":"object","properties":{"ReferenceItem":{"type":"object","example":{"QueueTimeoutURL":"https://internalsandbox.safaricom.co.ke/mpesa/b2cresults/v1/submit"},"additionalProperties":true}},"example":{"ReferenceItem":{"QueueTimeoutURL":"https://internalsandbox.safaricom.co.ke/mpesa/b2cresults/v1/submit"}}},"Result":{"type":"object","properties":{"ConversationId":{"type":"string","description":"Unique identifier for the transaction request.","example":"236543-276372-2"},"OriginatorConversationId":{"type":"string","description":"Unique identifier for the transaction request.","example":"AG_2376487236_126732989KJHJKH"},"ResultCode":{"type":"integer","description":"Numeric status code indicating the status of the transaction processing","example":0,"format":"int64"},"ResultDesc":{"type":"string","description":"Message from the API that gives the status of the request","example":"Initiator information is invalid"},"ResultType":{"type":"integer","description":"Status code indicating whether transaction was already sent to your listener","default":0,"example":0,"format":"int64"},"TransactionID":{"type":"string","description":"Unique M-PESA transaction ID for every payment request.","example":"LHG31AA5TX"}},"example":{"ConversationId":"236543-276372-2","OriginatorConversationId":"AG_2376487236_126732989KJHJKH","ResultCode":0,"ResultDesc":"Initiator information is invalid","ResultType":0,"TransactionID":"LHG31AA5TX"}},"ResultParameters":{"type":"object","properties":{"ResultParameter":{"type":"array","items":{"$ref":"#/definitions/B2CResultParametersRequestBody"},"example":[{"B2CChargesPaidAccountAvailableFunds":236543.9,"B2CRecipientIsRegisteredCustomer":"Y","B2CUtilityAccountAvailableFunds":23654.5,"B2CWorkingAccountAvailableFunds":2000,"ReceiverPartyPublicName":"254722000000 - Safaricom PLC","TransactionAmount":8000,"TransactionCompletedDateTime":"17.07.2017 10:54:57","TransactionReceipt":"LGH3197RIB"},{"B2CChargesPaidAccountAvailableFunds":236543.9,"B2CRecipientIsRegisteredCustomer":"Y","B2CUtilityAccountAvailableFunds":23654.5,"B2CWorkingAccountAvailableFunds":2000,"ReceiverPartyPublicName":"254722000000 - Safaricom PLC","TransactionAmount":8000,"TransactionCompletedDateTime":"17.07.2017 10:54:57","TransactionReceipt":"LGH3197RIB"},{"B2CChargesPaidAccountAvailableFunds":236543.9,"B2CRecipientIsRegisteredCustomer":"Y","B2CUtilityAccountAvailableFunds":23654.5,"B2CWorkingAccountAvailableFunds":2000,"ReceiverPartyPublicName":"254722000000 - Safaricom PLC","TransactionAmount":8000,"TransactionCompletedDateTime":"17.07.2017 10:54:57","TransactionReceipt":"LGH3197RIB"},{"B2CChargesPaidAccountAvailableFunds":236543.9,"B2CRecipientIsRegisteredCustomer":"Y","B2CUtilityAccountAvailableFunds":23654.5,"B2CWorkingAccountAvailableFunds":2000,"ReceiverPartyPublicName":"254722000000 - Safaricom PLC","TransactionAmount":8000,"TransactionCompletedDateTime":"17.07.2017 10:54:57","TransactionReceipt":"LGH3197RIB"}]}},"example":{"ResultParameter":[{"B2CChargesPaidAccountAvailableFunds":236543.9,"B2CRecipientIsRegisteredCustomer":"Y","B2CUtilityAccountAvailableFunds":23654.5,"B2CWorkingAccountAvailableFunds":2000,"ReceiverPartyPublicName":"254722000000 - Safaricom PLC","TransactionAmount":8000,"TransactionCompletedDateTime":"17.07.2017 10:54:57","TransactionReceipt":"LGH3197RIB"},{"B2CChargesPaidAccountAvailableFunds":236543.9,"B2CRecipientIsRegisteredCustomer":"Y","B2CUtilityAccountAvailableFunds":23654.5,"B2CWorkingAccountAvailableFunds":2000,"ReceiverPartyPublicName":"254722000000 - Safaricom PLC","TransactionAmount":8000,"TransactionCompletedDateTime":"17.07.2017 10:54:57","TransactionReceipt":"LGH3197RIB"},{"B2CChargesPaidAccountAvailableFunds":236543.9,"B2CRecipientIsRegisteredCustomer":"Y","B2CUtilityAccountAvailableFunds":23654.5,"B2CWorkingAccountAvailableFunds":2000,"ReceiverPartyPublicName":"254722000000 - Safaricom PLC","TransactionAmount":8000,"TransactionCompletedDateTime":"17.07.2017 10:54:57","TransactionReceipt":"LGH3197RIB"}]}}},"example":{"ReferenceData":{"ReferenceItem":{"QueueTimeoutURL":"https://internalsandbox.safaricom.co.ke/mpesa/b2cresults/v1/submit"}},"Result":{"ConversationId":"236543-276372-2","OriginatorConversationId":"AG_2376487236_126732989KJHJKH","ResultCode":0,"ResultDesc":"Initiator information is invalid","ResultType":0,"TransactionID":"LHG31AA5TX"},"ResultParameters":{"ResultParameter":[{"B2CChargesPaidAccountAvailableFunds":236543.9,"B2CRecipientIsRegisteredCustomer":"Y","B2CUtilityAccountAvailableFunds":23654.5,"B2CWorkingAccountAvailableFunds":2000,"ReceiverPartyPublicName":"254722000000 - Safaricom PLC","TransactionAmount":8000,"TransactionCompletedDateTime":"17.07.2017 10:54:57","TransactionReceipt":"LGH3197RIB"},{"B2CChargesPaidAccountAvailableFunds":236543.9,"B2CRecipientIsRegisteredCustomer":"Y","B2CUtilityAccountAvailableFunds":23654.5,"B2CWorkingAccountAvailableFunds":2000,"ReceiverPartyPublicName":"254722000000 - Safaricom PLC","TransactionAmount":8000,"TransactionCompletedDateTime":"17.07.2017 10:54:57","TransactionReceipt":"LGH3197RIB"},{"B2CChargesPaidAccountAvailableFunds":236543.9,"B2CRecipientIsRegisteredCustomer":"Y","B2CUtilityAccountAvailableFunds":23654.5,"B2CWorkingAccountAvailableFunds":2000,"ReceiverPartyPublicName":"254722000000 - Safaricom PLC","TransactionAmount":8000,"TransactionCompletedDateTime":"17.07.2017 10:54:57","TransactionReceipt":"LGH3197RIB"}]}}},"MpesaB2CTimeoutRequestBody":{"title":"MpesaB2CTimeoutRequestBody","type":"object","properties":{"ReferenceData":{"type":"object","properties":{"ReferenceItem":{"type":"object","example":{"QueueTimeoutURL":"https://internalsandbox.safaricom.co.ke/mpesa/b2cresults/v1/submit"},"additionalProperties":true}},"example":{"ReferenceItem":{"QueueTimeoutURL":"https://internalsandbox.safaricom.co.ke/mpesa/b2cresults/v1/submit"}}},"Result":{"type":"object","properties":{"ConversationId":{"type":"string","description":"Unique identifier for the transaction request.","example":"236543-276372-2"},"OriginatorConversationId":{"type":"string","description":"Unique identifier for the transaction request.","example":"AG_2376487236_126732989KJHJKH"},"ResultCode":{"type":"integer","description":"Numeric status code indicating the status of the transaction processing","example":0,"format":"int64"},"ResultDesc":{"type":"string","description":"Message from the API that gives the status of the request","example":"Initiator information is invalid"},"ResultType":{"type":"integer","description":"Status code indicating whether transaction was already sent to your listener","default":0,"example":0,"format":"int64"},"TransactionID":{"type":"string","description":"Unique M-PESA transaction ID for every payment request.","example":"LHG31AA5TX"}},"example":{"ConversationId":"236543-276372-2","OriginatorConversationId":"AG_2376487236_126732989KJHJKH","ResultCode":0,"ResultDesc":"Initiator information is invalid","ResultType":0,"TransactionID":"LHG31AA5TX"}},"ResultParameters":{"type":"object","properties":{"ResultParameter":{"type":"array","items":{"$ref":"#/definitions/B2CResultParametersRequestBody"},"example":[{"B2CChargesPaidAccountAvailableFunds":236543.9,"B2CRecipientIsRegisteredCustomer":"Y","B2CUtilityAccountAvailableFunds":23654.5,"B2CWorkingAccountAvailableFunds":2000,"ReceiverPartyPublicName":"254722000000 - Safaricom PLC","TransactionAmount":8000,"TransactionCompletedDateTime":"17.07.2017 10:54:57","TransactionReceipt":"LGH3197RIB"},{"B2CChargesPaidAccountAvailableFunds":236543.9,"B2CRecipientIsRegisteredCustomer":"Y","B2CUtilityAccountAvailableFunds":23654.5,"B2CWorkingAccountAvailableFunds":2000,"ReceiverPartyPublicName":"254722000000 - Safaricom PLC","TransactionAmount":8000,"TransactionCompletedDateTime":"17.07.2017 10:54:57","TransactionReceipt":"LGH3197RIB"}]}},"example":{"ResultParameter":[{"B2CChargesPaidAccountAvailableFunds":236543.9,"B2CRecipientIsRegisteredCustomer":"Y","B2CUtilityAccountAvailableFunds":23654.5,"B2CWorkingAccountAvailableFunds":2000,"ReceiverPartyPublicName":"254722000000 - Safaricom PLC","TransactionAmount":8000,"TransactionCompletedDateTime":"17.07.2017 10:54:57","TransactionReceipt":"LGH3197RIB"},{"B2CChargesPaidAccountAvailableFunds":236543.9,"B2CRecipientIsRegisteredCustomer":"Y","B2CUtilityAccountAvailableFunds":23654.5,"B2CWorkingAccountAvailableFunds":2000,"ReceiverPartyPublicName":"254722000000 - Safaricom PLC","TransactionAmount":8000,"TransactionCompletedDateTime":"17.07.2017 10:54:57","TransactionReceipt":"LGH3197RIB"}]}}},"example":{"ReferenceData":{"ReferenceItem":{"QueueTimeoutURL":"https://internalsandbox.safaricom.co.ke/mpesa/b2cresults/v1/submit"}},"Result":{"ConversationId":"236543-276372-2","OriginatorConversationId":"AG_2376487236_126732989KJHJKH","ResultCode":0,"ResultDesc":"Initiator information is invalid","ResultType":0,"TransactionID":"LHG31AA5TX"},"ResultParameters":{"ResultParameter":[{"B2CChargesPaidAccountAvailableFunds":236543.9,"B2CRecipientIsRegisteredCustomer":"Y","B2CUtilityAccountAvailableFunds":23654.5,"B2CWorkingAccountAvailableFunds":2000,"ReceiverPartyPublicName":"254722000000 - Safaricom PLC","TransactionAmount":8000,"TransactionCompletedDateTime":"17.07.2017 10:54:57","TransactionReceipt":"LGH3197RIB"},{"B2CChargesPaidAccountAvailableFunds":236543.9,"B2CRecipientIsRegisteredCustomer":"Y","B2CUtilityAccountAvailableFunds":23654.5,"B2CWorkingAccountAvailableFunds":2000,"ReceiverPartyPublicName":"254722000000 - Safaricom PLC","TransactionAmount":8000,"TransactionCompletedDateTime":"17.07.2017 10:54:57","TransactionReceipt":"LGH3197RIB"},{"B2CChargesPaidAccountAvailableFunds":236543.9,"B2CRecipientIsRegisteredCustomer":"Y","B2CUtilityAccountAvailableFunds":23654.5,"B2CWorkingAccountAvailableFunds":2000,"ReceiverPartyPublicName":"254722000000 - Safaricom PLC","TransactionAmount":8000,"TransactionCompletedDateTime":"17.07.2017 10:54:57","TransactionReceipt":"LGH3197RIB"}]}}},"MpesaC2BConfirmationRequestBody":{"title":"MpesaC2BConfirmationRequestBody","type":"object","properties":{"BillRefNumber":{"type":"string","description":"Account number for which the customer is making the payment","example":"w1o","maxLength":20},"BusinessShortCode":{"type":"integer","description":"Organizations shortcode (Paybill or Buygoods)","example":654321,"format":"int64"},"FirstName":{"type":"string","description":"First Name of the customer making the payment.","example":"John"},"InvoiceNumber":{"type":"string","example":"Aperiam porro molestiae."},"LastName":{"type":"string","description":"Last Name of the customer making payment.","example":"Jane"},"MSISDN":{"type":"integer","description":"Mobile number of the customer making the payment.","example":553116540879448616,"format":"int64"},"MiddleName":{"type":"string","description":"Middle Name of the customer making the payment.","example":"Doe"},"OrgAccountBalance":{"type":"integer","description":"Current utility account balance of the payment receiving organization shortcode","example":30671,"format":"int64"},"ThirdPartyTransID":{"type":"string","example":"Minima repellat sed beatae omnis exercitationem quod."},"TransAmount":{"type":"integer","description":"The Amount transacted normally a numeric value","example":100,"format":"int64"},"TransID":{"type":"string","description":"Unique M-Pesa transaction ID for every payment request","example":"LHG31AA5TX"},"TransTime":{"type":"string","description":"Timestamp of the transaction","example":"20180713154301","format":"date-time"},"TransactionType":{"type":"string","description":"Transaction type specified during the payment request.","example":"Pay Bill","enum":["Buy Goods","Pay Bill"]}},"example":{"BillRefNumber":"ql2","BusinessShortCode":654321,"FirstName":"John","InvoiceNumber":"Delectus itaque nihil.","LastName":"Jane","MSISDN":6155933688297873645,"MiddleName":"Doe","OrgAccountBalance":30671,"ThirdPartyTransID":"Quas porro.","TransAmount":100,"TransID":"LHG31AA5TX","TransTime":"20180713154301","TransactionType":"Buy Goods"}},"MpesaC2BValidationRequestBody":{"title":"MpesaC2BValidationRequestBody","type":"object","properties":{"BillRefNumber":{"type":"string","description":"Account number for which the customer is making the payment","example":"t07","maxLength":20},"BusinessShortCode":{"type":"integer","description":"Organizations shortcode (Paybill or Buygoods)","example":654321,"format":"int64"},"FirstName":{"type":"string","description":"First Name of the customer making the payment.","example":"John"},"InvoiceNumber":{"type":"string","example":"Omnis voluptas id iste cumque aut omnis."},"LastName":{"type":"string","description":"Last Name of the customer making payment.","example":"Jane"},"MSISDN":{"type":"integer","description":"Mobile number of the customer making the payment.","example":6936643202856870088,"format":"int64"},"MiddleName":{"type":"string","description":"Middle Name of the customer making the payment.","example":"Doe"},"OrgAccountBalance":{"type":"integer","description":"Current utility account balance of the payment receiving organization shortcode","example":30671,"format":"int64"},"ThirdPartyTransID":{"type":"string","example":"Perferendis voluptas voluptas deleniti maxime."},"TransAmount":{"type":"integer","description":"The Amount transacted normally a numeric value","example":100,"format":"int64"},"TransID":{"type":"string","description":"Unique M-Pesa transaction ID for every payment request","example":"LHG31AA5TX"},"TransTime":{"type":"string","description":"Timestamp of the transaction","example":"20180713154301","format":"date-time"},"TransactionType":{"type":"string","description":"Transaction type specified during the payment request.","example":"Buy Goods","enum":["Buy Goods","Pay Bill"]}},"example":{"BillRefNumber":"6p4","BusinessShortCode":654321,"FirstName":"John","InvoiceNumber":"Expedita et veritatis.","LastName":"Jane","MSISDN":6934802946222159529,"MiddleName":"Doe","OrgAccountBalance":30671,"ThirdPartyTransID":"Tempora libero perferendis.","TransAmount":100,"TransID":"LHG31AA5TX","TransTime":"20180713154301","TransactionType":"Pay Bill"}},"MpesaReversalResultRequestBody":{"title":"MpesaReversalResultRequestBody","type":"object","properties":{"Result":{"type":"object","properties":{"ConversationId":{"type":"string","description":"Unique identifier for the transaction request.","example":"236543-276372-2"},"OriginatorConversationId":{"type":"string","description":"Unique identifier for the transaction request.","example":"AG_2376487236_126732989KJHJKH"},"ReferenceData":{"type":"object","properties":{"ReferenceItem":{"type":"object","example":{"QueueTimeoutURL":"https://internalsandbox.safaricom.co.ke/mpesa/reversalresults/v1/submit"},"additionalProperties":true}},"example":{"ReferenceItem":{"QueueTimeoutURL":"https://internalsandbox.safaricom.co.ke/mpesa/reversalresults/v1/submit"}}},"ResultCode":{"type":"integer","description":"Numeric status code indicating the status of the transaction processing","example":0,"format":"int64"},"ResultDesc":{"type":"string","description":"Message from the API that gives the status of the request","example":"Initiator information is invalid"},"ResultType":{"type":"integer","description":"Status code indicating whether transaction was already sent to your listener","default":0,"example":0,"format":"int64"},"TransactionID":{"type":"string","description":"Unique M-PESA transaction ID for every payment request.","example":"LHG31AA5TX"}},"example":{"ConversationId":"236543-276372-2","OriginatorConversationId":"AG_2376487236_126732989KJHJKH","ReferenceData":{"ReferenceItem":{"QueueTimeoutURL":"https://internalsandbox.safaricom.co.ke/mpesa/reversalresults/v1/submit"}},"ResultCode":0,"ResultDesc":"Initiator information is invalid","ResultType":0,"TransactionID":"LHG31AA5TX"}}},"example":{"Result":{"ConversationId":"236543-276372-2","OriginatorConversationId":"AG_2376487236_126732989KJHJKH","ReferenceData":{"ReferenceItem":{"QueueTimeoutURL":"https://internalsandbox.safaricom.co.ke/mpesa/reversalresults/v1/submit"}},"ResultCode":0,"ResultDesc":"Initiator information is invalid","ResultType":0,"TransactionID":"LHG31AA5TX"}}},"MpesaReversalTimeoutRequestBody":{"title":"MpesaReversalTimeoutRequestBody","type":"object","properties":{"Result":{"type":"object","properties":{"ConversationId":{"type":"string","description":"Unique identifier for the transaction request.","example":"236543-276372-2"},"OriginatorConversationId":{"type":"string","description":"Unique identifier for the transaction request.","example":"AG_2376487236_126732989KJHJKH"},"ReferenceData":{"type":"object","properties":{"ReferenceItem":{"type":"object","example":{"QueueTimeoutURL":"https://internalsandbox.safaricom.co.ke/mpesa/reversalresults/v1/submit"},"additionalProperties":true}},"example":{"ReferenceItem":{"QueueTimeoutURL":"https://internalsandbox.safaricom.co.ke/mpesa/reversalresults/v1/submit"}}},"ResultCode":{"type":"integer","description":"Numeric status code indicating the status of the transaction processing","example":0,"format":"int64"},"ResultDesc":{"type":"string","description":"Message from the API that gives the status of the request","example":"Initiator information is invalid"},"ResultType":{"type":"integer","description":"Status code indicating whether transaction was already sent to your listener","default":0,"example":0,"format":"int64"},"TransactionID":{"type":"string","description":"Unique M-PESA transaction ID for every payment request.","example":"LHG31AA5TX"}},"example":{"ConversationId":"236543-276372-2","OriginatorConversationId":"AG_2376487236_126732989KJHJKH","ReferenceData":{"ReferenceItem":{"QueueTimeoutURL":"https://internalsandbox.safaricom.co.ke/mpesa/reversalresults/v1/submit"}},"ResultCode":0,"ResultDesc":"Initiator information is invalid","ResultType":0,"TransactionID":"LHG31AA5TX"}}},"example":{"Result":{"ConversationId":"236543-276372-2","OriginatorConversationId":"AG_2376487236_126732989KJHJKH","ReferenceData":{"ReferenceItem":{"QueueTimeoutURL":"https://internalsandbox.safaricom.co.ke/mpesa/reversalresults/v1/submit"}},"ResultCode":0,"ResultDesc":"Initiator information is invalid","ResultType":0,"TransactionID":"LHG31AA5TX"}}},"MpesaTransactionStatusResultRequestBody":{"title":"MpesaTransactionStatusResultRequestBody","type":"object","properties":{"Result":{"type":"object","properties":{"ConversationId":{"type":"string","description":"Unique identifier for the transaction request.","example":"236543-276372-2"},"OriginatorConversationId":{"type":"string","description":"Unique identifier for the transaction request.","example":"AG_2376487236_126732989KJHJKH"},"ReferenceData":{"type":"object","properties":{"ReferenceItem":{"type":"object","example":{"Occasion":"Occasion"},"additionalProperties":true}},"example":{"ReferenceItem":{"Occasion":"Occasion"}}},"ResultCode":{"type":"integer","description":"Numeric status code indicating the status of the transaction processing","example":0,"format":"int64"},"ResultDesc":{"type":"string","description":"Message from the API that gives the status of the request","example":"Initiator information is invalid"},"ResultParameters":{"type":"object","properties":{"ResultParameter":{"type":"array","items":{"$ref":"#/definitions/TransactionStatusResultParameterRequestBody"},"example":[{"Amount":10,"ConversationID":"AG_20170727_00004492b1b6d0078fbe","CreditPartyName":"254708374149 - John Doe","DebitAccountType":"Utility Account","DebitPartyCharges":"Fee For B2C Payment|KES|33.00","DebitPartyName":"600134 - Safaricom157","FinalisedTime":"20170727101415","InitiatedTime":"20170727101415","Originator Conversation ID":"19455-773836-1","ReasonType":"Salary Payment via API","ReceiptNo":"LGR919G2AV","TransactionReason":"Transaction Reason","TransactionStatus":"Completed"},{"Amount":10,"ConversationID":"AG_20170727_00004492b1b6d0078fbe","CreditPartyName":"254708374149 - John Doe","DebitAccountType":"Utility Account","DebitPartyCharges":"Fee For B2C Payment|KES|33.00","DebitPartyName":"600134 - Safaricom157","FinalisedTime":"20170727101415","InitiatedTime":"20170727101415","Originator Conversation ID":"19455-773836-1","ReasonType":"Salary Payment via API","ReceiptNo":"LGR919G2AV","TransactionReason":"Transaction Reason","TransactionStatus":"Completed"},{"Amount":10,"ConversationID":"AG_20170727_00004492b1b6d0078fbe","CreditPartyName":"254708374149 - John Doe","DebitAccountType":"Utility Account","DebitPartyCharges":"Fee For B2C Payment|KES|33.00","DebitPartyName":"600134 - Safaricom157","FinalisedTime":"20170727101415","InitiatedTime":"20170727101415","Originator Conversation ID":"19455-773836-1","ReasonType":"Salary Payment via API","ReceiptNo":"LGR919G2AV","TransactionReason":"Transaction Reason","TransactionStatus":"Completed"}]}},"example":{"ResultParameter":[{"Amount":10,"ConversationID":"AG_20170727_00004492b1b6d0078fbe","CreditPartyName":"254708374149 - John Doe","DebitAccountType":"Utility Account","DebitPartyCharges":"Fee For B2C Payment|KES|33.00","DebitPartyName":"600134 - Safaricom157","FinalisedTime":"20170727101415","InitiatedTime":"20170727101415","Originator Conversation ID":"19455-773836-1","ReasonType":"Salary Payment via API","ReceiptNo":"LGR919G2AV","TransactionReason":"Transaction Reason","TransactionStatus":"Completed"},{"Amount":10,"ConversationID":"AG_20170727_00004492b1b6d0078fbe","CreditPartyName":"254708374149 - John Doe","DebitAccountType":"Utility Account","DebitPartyCharges":"Fee For B2C Payment|KES|33.00","DebitPartyName":"600134 - Safaricom157","FinalisedTime":"20170727101415","InitiatedTime":"20170727101415","Originator Conversation ID":"19455-773836-1","ReasonType":"Salary Payment via API","ReceiptNo":"LGR919G2AV","TransactionReason":"Transaction Reason","TransactionStatus":"Completed"},{"Amount":10,"ConversationID":"AG_20170727_00004492b1b6d0078fbe","CreditPartyName":"254708374149 - John Doe","DebitAccountType":"Utility Account","DebitPartyCharges":"Fee For B2C Payment|KES|33.00","DebitPartyName":"600134 - Safaricom157","FinalisedTime":"20170727101415","InitiatedTime":"20170727101415","Originator Conversation ID":"19455-773836-1","ReasonType":"Salary Payment via API","ReceiptNo":"LGR919G2AV","TransactionReason":"Transaction Reason","TransactionStatus":"Completed"},{"Amount":10,"ConversationID":"AG_20170727_00004492b1b6d0078fbe","CreditPartyName":"254708374149 - John Doe","DebitAccountType":"Utility Account","DebitPartyCharges":"Fee For B2C Payment|KES|33.00","DebitPartyName":"600134 - Safaricom157","FinalisedTime":"20170727101415","InitiatedTime":"20170727101415","Originator Conversation ID":"19455-773836-1","ReasonType":"Salary Payment via API","ReceiptNo":"LGR919G2AV","TransactionReason":"Transaction Reason","TransactionStatus":"Completed"}]}},"ResultType":{"type":"integer","description":"Status code indicating whether transaction was already sent to your listener","default":0,"example":0,"format":"int64"},"TransactionID":{"type":"string","description":"Unique M-PESA transaction ID for every payment request.","example":"LHG31AA5TX"}},"example":{"ConversationId":"236543-276372-2","OriginatorConversationId":"AG_2376487236_126732989KJHJKH","ReferenceData":{"ReferenceItem":{"Occasion":"Occasion"}},"ResultCode":0,"ResultDesc":"Initiator information is invalid","ResultParameters":{"ResultParameter":[{"Amount":10,"ConversationID":"AG_20170727_00004492b1b6d0078fbe","CreditPartyName":"254708374149 - John Doe","DebitAccountType":"Utility Account","DebitPartyCharges":"Fee For B2C Payment|KES|33.00","DebitPartyName":"600134 - Safaricom157","FinalisedTime":"20170727101415","InitiatedTime":"20170727101415","Originator Conversation ID":"19455-773836-1","ReasonType":"Salary Payment via API","ReceiptNo":"LGR919G2AV","TransactionReason":"Transaction Reason","TransactionStatus":"Completed"},{"Amount":10,"ConversationID":"AG_20170727_00004492b1b6d0078fbe","CreditPartyName":"254708374149 - John Doe","DebitAccountType":"Utility Account","DebitPartyCharges":"Fee For B2C Payment|KES|33.00","DebitPartyName":"600134 - Safaricom157","FinalisedTime":"20170727101415","InitiatedTime":"20170727101415","Originator Conversation ID":"19455-773836-1","ReasonType":"Salary Payment via API","ReceiptNo":"LGR919G2AV","TransactionReason":"Transaction Reason","TransactionStatus":"Completed"},{"Amount":10,"ConversationID":"AG_20170727_00004492b1b6d0078fbe","CreditPartyName":"254708374149 - John Doe","DebitAccountType":"Utility Account","DebitPartyCharges":"Fee For B2C Payment|KES|33.00","DebitPartyName":"600134 - Safaricom157","FinalisedTime":"20170727101415","InitiatedTime":"20170727101415","Originator Conversation ID":"19455-773836-1","ReasonType":"Salary Payment via API","ReceiptNo":"LGR919G2AV","TransactionReason":"Transaction Reason","TransactionStatus":"Completed"}]},"ResultType":0,"TransactionID":"LHG31AA5TX"}}},"example":{"Result":{"ConversationId":"236543-276372-2","OriginatorConversationId":"AG_2376487236_126732989KJHJKH","ReferenceData":{"ReferenceItem":{"Occasion":"Occasion"}},"ResultCode":0,"ResultDesc":"Initiator information is invalid","ResultParameters":{"ResultParameter":[{"Amount":10,"ConversationID":"AG_20170727_00004492b1b6d0078fbe","CreditPartyName":"254708374149 - John Doe","DebitAccountType":"Utility Account","DebitPartyCharges":"Fee For B2C Payment|KES|33.00","DebitPartyName":"600134 - Safaricom157","FinalisedTime":"20170727101415","InitiatedTime":"20170727101415","Originator Conversation ID":"19455-773836-1","ReasonType":"Salary Payment via API","ReceiptNo":"LGR919G2AV","TransactionReason":"Transaction Reason","TransactionStatus":"Completed"},{"Amount":10,"ConversationID":"AG_20170727_00004492b1b6d0078fbe","CreditPartyName":"254708374149 - John Doe","DebitAccountType":"Utility Account","DebitPartyCharges":"Fee For B2C Payment|KES|33.00","DebitPartyName":"600134 - Safaricom157","FinalisedTime":"20170727101415","InitiatedTime":"20170727101415","Originator Conversation ID":"19455-773836-1","ReasonType":"Salary Payment via API","ReceiptNo":"LGR919G2AV","TransactionReason":"Transaction Reason","TransactionStatus":"Completed"},{"Amount":10,"ConversationID":"AG_20170727_00004492b1b6d0078fbe","CreditPartyName":"254708374149 - John Doe","DebitAccountType":"Utility Account","DebitPartyCharges":"Fee For B2C Payment|KES|33.00","DebitPartyName":"600134 - Safaricom157","FinalisedTime":"20170727101415","InitiatedTime":"20170727101415","Originator Conversation ID":"19455-773836-1","ReasonType":"Salary Payment via API","ReceiptNo":"LGR919G2AV","TransactionReason":"Transaction Reason","TransactionStatus":"Completed"},{"Amount":10,"ConversationID":"AG_20170727_00004492b1b6d0078fbe","CreditPartyName":"254708374149 - John Doe","DebitAccountType":"Utility Account","DebitPartyCharges":"Fee For B2C Payment|KES|33.00","DebitPartyName":"600134 - Safaricom157","FinalisedTime":"20170727101415","InitiatedTime":"20170727101415","Originator Conversation ID":"19455-773836-1","ReasonType":"Salary Payment via API","ReceiptNo":"LGR919G2AV","TransactionReason":"Transaction Reason","TransactionStatus":"Completed"}]},"ResultType":0,"TransactionID":"LHG31AA5TX"}}},"MpesaTransactionStatusTimeoutRequestBody":{"title":"MpesaTransactionStatusTimeoutRequestBody","type":"object","properties":{"Result":{"type":"object","properties":{"ConversationId":{"type":"string","description":"Unique identifier for the transaction request.","example":"236543-276372-2"},"OriginatorConversationId":{"type":"string","description":"Unique identifier for the transaction request.","example":"AG_2376487236_126732989KJHJKH"},"ReferenceData":{"type":"object","properties":{"ReferenceItem":{"type":"object","example":{"Occasion":"Occasion"},"additionalProperties":true}},"example":{"ReferenceItem":{"Occasion":"Occasion"}}},"ResultCode":{"type":"integer","description":"Numeric status code indicating the status of the transaction processing","example":0,"format":"int64"},"ResultDesc":{"type":"string","description":"Message from the API that gives the status of the request","example":"Initiator information is invalid"},"ResultParameters":{"type":"object","properties":{"ResultParameter":{"type":"array","items":{"$ref":"#/definitions/TransactionStatusResultParameterRequestBody"},"example":[{"Amount":10,"ConversationID":"AG_20170727_00004492b1b6d0078fbe","CreditPartyName":"254708374149 - John Doe","DebitAccountType":"Utility Account","DebitPartyCharges":"Fee For B2C Payment|KES|33.00","DebitPartyName":"600134 - Safaricom157","FinalisedTime":"20170727101415","InitiatedTime":"20170727101415","Originator Conversation ID":"19455-773836-1","ReasonType":"Salary Payment via API","ReceiptNo":"LGR919G2AV","TransactionReason":"Transaction Reason","TransactionStatus":"Completed"},{"Amount":10,"ConversationID":"AG_20170727_00004492b1b6d0078fbe","CreditPartyName":"254708374149 - John Doe","DebitAccountType":"Utility Account","DebitPartyCharges":"Fee For B2C Payment|KES|33.00","DebitPartyName":"600134 - Safaricom157","FinalisedTime":"20170727101415","InitiatedTime":"20170727101415","Originator Conversation ID":"19455-773836-1","ReasonType":"Salary Payment via API","ReceiptNo":"LGR919G2AV","TransactionReason":"Transaction Reason","TransactionStatus":"Completed"},{"Amount":10,"ConversationID":"AG_20170727_00004492b1b6d0078fbe","CreditPartyName":"254708374149 - John Doe","DebitAccountType":"Utility Account","DebitPartyCharges":"Fee For B2C Payment|KES|33.00","DebitPartyName":"600134 - Safaricom157","FinalisedTime":"20170727101415","InitiatedTime":"20170727101415","Originator Conversation ID":"19455-773836-1","ReasonType":"Salary Payment via API","ReceiptNo":"LGR919G2AV","TransactionReason":"Transaction Reason","TransactionStatus":"Completed"}]}},"example":{"ResultParameter":[{"Amount":10,"ConversationID":"AG_20170727_00004492b1b6d0078fbe","CreditPartyName":"254708374149 - John Doe","DebitAccountType":"Utility Account","DebitPartyCharges":"Fee For B2C Payment|KES|33.00","DebitPartyName":"600134 - Safaricom157","FinalisedTime":"20170727101415","InitiatedTime":"20170727101415","Originator Conversation ID":"19455-773836-1","ReasonType":"Salary Payment via API","ReceiptNo":"LGR919G2AV","TransactionReason":"Transaction Reason","TransactionStatus":"Completed"},{"Amount":10,"ConversationID":"AG_20170727_00004492b1b6d0078fbe","CreditPartyName":"254708374149 - John Doe","DebitAccountType":"Utility Account","DebitPartyCharges":"Fee For B2C Payment|KES|33.00","DebitPartyName":"600134 - Safaricom157","FinalisedTime":"20170727101415","InitiatedTime":"20170727101415","Originator Conversation ID":"19455-773836-1","ReasonType":"Salary Payment via API","ReceiptNo":"LGR919G2AV","TransactionReason":"Transaction Reason","TransactionStatus":"Completed"},{"Amount":10,"ConversationID":"AG_20170727_00004492b1b6d0078fbe","CreditPartyName":"254708374149 - John Doe","DebitAccountType":"Utility Account","DebitPartyCharges":"Fee For B2C Payment|KES|33.00","DebitPartyName":"600134 - Safaricom157","FinalisedTime":"20170727101415","InitiatedTime":"20170727101415","Originator Conversation ID":"19455-773836-1","ReasonType":"Salary Payment via API","ReceiptNo":"LGR919G2AV","TransactionReason":"Transaction Reason","TransactionStatus":"Completed"},{"Amount":10,"ConversationID":"AG_20170727_00004492b1b6d0078fbe","CreditPartyName":"254708374149 - John Doe","DebitAccountType":"Utility Account","DebitPartyCharges":"Fee For B2C Payment|KES|33.00","DebitPartyName":"600134 - Safaricom157","FinalisedTime":"20170727101415","InitiatedTime":"20170727101415","Originator Conversation ID":"19455-773836-1","ReasonType":"Salary Payment via API","ReceiptNo":"LGR919G2AV","TransactionReason":"Transaction Reason","TransactionStatus":"Completed"}]}},"ResultType":{"type":"integer","description":"Status code indicating whether transaction was already sent to your listener","default":0,"example":0,"format":"int64"},"TransactionID":{"type":"string","description":"Unique M-PESA transaction ID for every payment request.","example":"LHG31AA5TX"}},"example":{"ConversationId":"236543-276372-2","OriginatorConversationId":"AG_2376487236_126732989KJHJKH","ReferenceData":{"ReferenceItem":{"Occasion":"Occasion"}},"ResultCode":0,"ResultDesc":"Initiator information is invalid","ResultParameters":{"ResultParameter":[{"Amount":10,"ConversationID":"AG_20170727_00004492b1b6d0078fbe","CreditPartyName":"254708374149 - John Doe","DebitAccountType":"Utility Account","DebitPartyCharges":"Fee For B2C Payment|KES|33.00","DebitPartyName":"600134 - Safaricom157","FinalisedTime":"20170727101415","InitiatedTime":"20170727101415","Originator Conversation ID":"19455-773836-1","ReasonType":"Salary Payment via API","ReceiptNo":"LGR919G2AV","TransactionReason":"Transaction Reason","TransactionStatus":"Completed"},{"Amount":10,"ConversationID":"AG_20170727_00004492b1b6d0078fbe","CreditPartyName":"254708374149 - John Doe","DebitAccountType":"Utility Account","DebitPartyCharges":"Fee For B2C Payment|KES|33.00","DebitPartyName":"600134 - Safaricom157","FinalisedTime":"20170727101415","InitiatedTime":"20170727101415","Originator Conversation ID":"19455-773836-1","ReasonType":"Salary Payment via API","ReceiptNo":"LGR919G2AV","TransactionReason":"Transaction Reason","TransactionStatus":"Completed"}]},"ResultType":0,"TransactionID":"LHG31AA5TX"}}},"example":{"Result":{"ConversationId":"236543-276372-2","OriginatorConversationId":"AG_2376487236_126732989KJHJKH","ReferenceData":{"ReferenceItem":{"Occasion":"Occasion"}},"ResultCode":0,"ResultDesc":"Initiator information is invalid","ResultParameters":{"ResultParameter":[{"Amount":10,"ConversationID":"AG_20170727_00004492b1b6d0078fbe","CreditPartyName":"254708374149 - John Doe","DebitAccountType":"Utility Account","DebitPartyCharges":"Fee For B2C Payment|KES|33.00","DebitPartyName":"600134 - Safaricom157","FinalisedTime":"20170727101415","InitiatedTime":"20170727101415","Originator Conversation ID":"19455-773836-1","ReasonType":"Salary Payment via API","ReceiptNo":"LGR919G2AV","TransactionReason":"Transaction Reason","TransactionStatus":"Completed"},{"Amount":10,"ConversationID":"AG_20170727_00004492b1b6d0078fbe","CreditPartyName":"254708374149 - John Doe","DebitAccountType":"Utility Account","DebitPartyCharges":"Fee For B2C Payment|KES|33.00","DebitPartyName":"600134 - Safaricom157","FinalisedTime":"20170727101415","InitiatedTime":"20170727101415","Originator Conversation ID":"19455-773836-1","ReasonType":"Salary Payment via API","ReceiptNo":"LGR919G2AV","TransactionReason":"Transaction Reason","TransactionStatus":"Completed"}]},"ResultType":0,"TransactionID":"LHG31AA5TX"}}},"ReversalResult":{"title":"ReversalResult","type":"object","properties":{"Result":{"type":"object","properties":{"ConversationId":{"type":"string","description":"Unique identifier for the transaction request.","example":"236543-276372-2"},"OriginatorConversationId":{"type":"string","description":"Unique identifier for the transaction request.","example":"AG_2376487236_126732989KJHJKH"},"ReferenceData":{"type":"object","properties":{"ReferenceItem":{"type":"object","example":{"QueueTimeoutURL":"https://internalsandbox.safaricom.co.ke/mpesa/reversalresults/v1/submit"},"additionalProperties":true}},"example":{"ReferenceItem":{"QueueTimeoutURL":"https://internalsandbox.safaricom.co.ke/mpesa/reversalresults/v1/submit"}}},"ResultCode":{"type":"integer","description":"Numeric status code indicating the status of the transaction processing","example":0,"format":"int64"},"ResultDesc":{"type":"string","description":"Message from the API that gives the status of the request","example":"Initiator information is invalid"},"ResultType":{"type":"integer","description":"Status code indicating whether transaction was already sent to your listener","default":0,"example":0,"format":"int64"},"TransactionID":{"type":"string","description":"Unique M-PESA transaction ID for every payment request.","example":"LHG31AA5TX"}},"example":{"ConversationId":"236543-276372-2","OriginatorConversationId":"AG_2376487236_126732989KJHJKH","ReferenceData":{"ReferenceItem":{"QueueTimeoutURL":"https://internalsandbox.safaricom.co.ke/mpesa/reversalresults/v1/submit"}},"ResultCode":0,"ResultDesc":"Initiator information is invalid","ResultType":0,"TransactionID":"LHG31AA5TX"}}},"description":"Successful Reversal Callback","example":{"Result":{"ConversationId":"236543-276372-2","OriginatorConversationId":"AG_2376487236_126732989KJHJKH","ReferenceData":{"ReferenceItem":{"QueueTimeoutURL":"https://internalsandbox.safaricom.co.ke/mpesa/reversalresults/v1/submit"}},"ResultCode":0,"ResultDesc":"Initiator information is invalid","ResultType":0,"TransactionID":"LHG31AA5TX"}}},"TransactionStatusResult":{"title":"TransactionStatusResult","type":"object","properties":{"Result":{"type":"object","properties":{"ConversationId":{"type":"string","description":"Unique identifier for the transaction request.","example":"236543-276372-2"},"OriginatorConversationId":{"type":"string","description":"Unique identifier for the transaction request.","example":"AG_2376487236_126732989KJHJKH"},"ReferenceData":{"type":"object","properties":{"ReferenceItem":{"type":"object","example":{"Occasion":"Occasion"},"additionalProperties":true}},"example":{"ReferenceItem":{"Occasion":"Occasion"}}},"ResultCode":{"type":"integer","description":"Numeric status code indicating the status of the transaction processing","example":0,"format":"int64"},"ResultDesc":{"type":"string","description":"Message from the API that gives the status of the request","example":"Initiator information is invalid"},"ResultParameters":{"type":"object","properties":{"ResultParameter":{"type":"array","items":{"$ref":"#/definitions/TransactionStatusResultParameter"},"example":[{"Amount":10,"ConversationID":"AG_20170727_00004492b1b6d0078fbe","CreditPartyName":"254708374149 - John Doe","DebitAccountType":"Utility Account","DebitPartyCharges":"Fee For B2C Payment|KES|33.00","DebitPartyName":"600134 - Safaricom157","FinalisedTime":"20170727101415","InitiatedTime":"20170727101415","Originator Conversation ID":"19455-773836-1","ReasonType":"Salary Payment via API","ReceiptNo":"LGR919G2AV","TransactionReason":"Transaction Reason","TransactionStatus":"Completed"},{"Amount":10,"ConversationID":"AG_20170727_00004492b1b6d0078fbe","CreditPartyName":"254708374149 - John Doe","DebitAccountType":"Utility Account","DebitPartyCharges":"Fee For B2C Payment|KES|33.00","DebitPartyName":"600134 - Safaricom157","FinalisedTime":"20170727101415","InitiatedTime":"20170727101415","Originator Conversation ID":"19455-773836-1","ReasonType":"Salary Payment via API","ReceiptNo":"LGR919G2AV","TransactionReason":"Transaction Reason","TransactionStatus":"Completed"}]}},"example":{"ResultParameter":[{"Amount":10,"ConversationID":"AG_20170727_00004492b1b6d0078fbe","CreditPartyName":"254708374149 - John Doe","DebitAccountType":"Utility Account","DebitPartyCharges":"Fee For B2C Payment|KES|33.00","DebitPartyName":"600134 - Safaricom157","FinalisedTime":"20170727101415","InitiatedTime":"20170727101415","Originator Conversation ID":"19455-773836-1","ReasonType":"Salary Payment via API","ReceiptNo":"LGR919G2AV","TransactionReason":"Transaction Reason","TransactionStatus":"Completed"},{"Amount":10,"ConversationID":"AG_20170727_00004492b1b6d0078fbe","CreditPartyName":"254708374149 - John Doe","DebitAccountType":"Utility Account","DebitPartyCharges":"Fee For B2C Payment|KES|33.00","DebitPartyName":"600134 - Safaricom157","FinalisedTime":"20170727101415","InitiatedTime":"20170727101415","Originator Conversation ID":"19455-773836-1","ReasonType":"Salary Payment via API","ReceiptNo":"LGR919G2AV","TransactionReason":"Transaction Reason","TransactionStatus":"Completed"},{"Amount":10,"ConversationID":"AG_20170727_00004492b1b6d0078fbe","CreditPartyName":"254708374149 - John Doe","DebitAccountType":"Utility Account","DebitPartyCharges":"Fee For B2C Payment|KES|33.00","DebitPartyName":"600134 - Safaricom157","FinalisedTime":"20170727101415","InitiatedTime":"20170727101415","Originator Conversation ID":"19455-773836-1","ReasonType":"Salary Payment via API","ReceiptNo":"LGR919G2AV","TransactionReason":"Transaction Reason","TransactionStatus":"Completed"},{"Amount":10,"ConversationID":"AG_20170727_00004492b1b6d0078fbe","CreditPartyName":"254708374149 - John Doe","DebitAccountType":"Utility Account","DebitPartyCharges":"Fee For B2C Payment|KES|33.00","DebitPartyName":"600134 - Safaricom157","FinalisedTime":"20170727101415","InitiatedTime":"20170727101415","Originator Conversation ID":"19455-773836-1","ReasonType":"Salary Payment via API","ReceiptNo":"LGR919G2AV","TransactionReason":"Transaction Reason","TransactionStatus":"Completed"}]}},"ResultType":{"type":"integer","description":"Status code indicating whether transaction was already sent to your listener","default":0,"example":0,"format":"int64"},"TransactionID":{"type":"string","description":"Unique M-PESA transaction ID for every payment request.","example":"LHG31AA5TX"}},"example":{"ConversationId":"236543-276372-2","OriginatorConversationId":"AG_2376487236_126732989KJHJKH","ReferenceData":{"ReferenceItem":{"Occasion":"Occasion"}},"ResultCode":0,"ResultDesc":"Initiator information is invalid","ResultParameters":{"ResultParameter":[{"Amount":10,"ConversationID":"AG_20170727_00004492b1b6d0078fbe","CreditPartyName":"254708374149 - John Doe","DebitAccountType":"Utility Account","DebitPartyCharges":"Fee For B2C Payment|KES|33.00","DebitPartyName":"600134 - Safaricom157","FinalisedTime":"20170727101415","InitiatedTime":"20170727101415","Originator Conversation ID":"19455-773836-1","ReasonType":"Salary Payment via API","ReceiptNo":"LGR919G2AV","TransactionReason":"Transaction Reason","TransactionStatus":"Completed"},{"Amount":10,"ConversationID":"AG_20170727_00004492b1b6d0078fbe","CreditPartyName":"254708374149 - John Doe","DebitAccountType":"Utility Account","DebitPartyCharges":"Fee For B2C Payment|KES|33.00","DebitPartyName":"600134 - Safaricom157","FinalisedTime":"20170727101415","InitiatedTime":"20170727101415","Originator Conversation ID":"19455-773836-1","ReasonType":"Salary Payment via API","ReceiptNo":"LGR919G2AV","TransactionReason":"Transaction Reason","TransactionStatus":"Completed"},{"Amount":10,"ConversationID":"AG_20170727_00004492b1b6d0078fbe","CreditPartyName":"254708374149 - John Doe","DebitAccountType":"Utility Account","DebitPartyCharges":"Fee For B2C Payment|KES|33.00","DebitPartyName":"600134 - Safaricom157","FinalisedTime":"20170727101415","InitiatedTime":"20170727101415","Originator Conversation ID":"19455-773836-1","ReasonType":"Salary Payment via API","ReceiptNo":"LGR919G2AV","TransactionReason":"Transaction Reason","TransactionStatus":"Completed"},{"Amount":10,"ConversationID":"AG_20170727_00004492b1b6d0078fbe","CreditPartyName":"254708374149 - John Doe","DebitAccountType":"Utility Account","DebitPartyCharges":"Fee For B2C Payment|KES|33.00","DebitPartyName":"600134 - Safaricom157","FinalisedTime":"20170727101415","InitiatedTime":"20170727101415","Originator Conversation ID":"19455-773836-1","ReasonType":"Salary Payment via API","ReceiptNo":"LGR919G2AV","TransactionReason":"Transaction Reason","TransactionStatus":"Completed"}]},"ResultType":0,"TransactionID":"LHG31AA5TX"}}},"example":{"Result":{"ConversationId":"236543-276372-2","OriginatorConversationId":"AG_2376487236_126732989KJHJKH","ReferenceData":{"ReferenceItem":{"Occasion":"Occasion"}},"ResultCode":0,"ResultDesc":"Initiator information is invalid","ResultParameters":{"ResultParameter":[{"Amount":10,"ConversationID":"AG_20170727_00004492b1b6d0078fbe","CreditPartyName":"254708374149 - John Doe","DebitAccountType":"Utility Account","DebitPartyCharges":"Fee For B2C Payment|KES|33.00","DebitPartyName":"600134 - Safaricom157","FinalisedTime":"20170727101415","InitiatedTime":"20170727101415","Originator Conversation ID":"19455-773836-1","ReasonType":"Salary Payment via API","ReceiptNo":"LGR919G2AV","TransactionReason":"Transaction Reason","TransactionStatus":"Completed"},{"Amount":10,"ConversationID":"AG_20170727_00004492b1b6d0078fbe","CreditPartyName":"254708374149 - John Doe","DebitAccountType":"Utility Account","DebitPartyCharges":"Fee For B2C Payment|KES|33.00","DebitPartyName":"600134 - Safaricom157","FinalisedTime":"20170727101415","InitiatedTime":"20170727101415","Originator Conversation ID":"19455-773836-1","ReasonType":"Salary Payment via API","ReceiptNo":"LGR919G2AV","TransactionReason":"Transaction Reason","TransactionStatus":"Completed"}]},"ResultType":0,"TransactionID":"LHG31AA5TX"}}},"TransactionStatusResultParameter":{"title":"TransactionStatusResultParameter","type":"object","properties":{"Amount":{"type":"integer","example":10,"format":"int64"},"ConversationID":{"type":"string","example":"AG_20170727_00004492b1b6d0078fbe"},"CreditPartyName":{"type":"string","example":"254708374149 - John Doe"},"DebitAccountType":{"type":"string","example":"Utility Account"},"DebitPartyCharges":{"type":"string","example":"Fee For B2C Payment|KES|33.00"},"DebitPartyName":{"type":"string","example":"600134 - Safaricom157"},"FinalisedTime":{"type":"string","example":"20170727101415","format":"date-time"},"InitiatedTime":{"type":"string","example":"20170727101415","format":"date-time"},"Originator Conversation ID":{"type":"string","example":"19455-773836-1"},"ReasonType":{"type":"string","example":"Salary Payment via API"},"ReceiptNo":{"type":"string","example":"LGR919G2AV"},"TransactionReason":{"type":"string","example":"Transaction Reason"},"TransactionStatus":{"type":"string","example":"Completed"}},"example":{"Amount":10,"ConversationID":"AG_20170727_00004492b1b6d0078fbe","CreditPartyName":"254708374149 - John Doe","DebitAccountType":"Utility Account","DebitPartyCharges":"Fee For B2C Payment|KES|33.00","DebitPartyName":"600134 - Safaricom157","FinalisedTime":"20170727101415","InitiatedTime":"20170727101415","Originator Conversation ID":"19455-773836-1","ReasonType":"Salary Payment via API","ReceiptNo":"LGR919G2AV","TransactionReason":"Transaction Reason","TransactionStatus":"Completed"}},"TransactionStatusResultParameterRequestBody":{"title":"TransactionStatusResultParameterRequestBody","type":"object","properties":{"Amount":{"type":"integer","example":10,"format":"int64"},"ConversationID":{"type":"string","example":"AG_20170727_00004492b1b6d0078fbe"},"CreditPartyName":{"type":"string","example":"254708374149 - John Doe"},"DebitAccountType":{"type":"string","example":"Utility Account"},"DebitPartyCharges":{"type":"string","example":"Fee For B2C Payment|KES|33.00"},"DebitPartyName":{"type":"string","example":"600134 - Safaricom157"},"FinalisedTime":{"type":"string","example":"20170727101415","format":"date-time"},"InitiatedTime":{"type":"string","example":"20170727101415","format":"date-time"},"Originator Conversation ID":{"type":"string","example":"19455-773836-1"},"ReasonType":{"type":"string","example":"Salary Payment via API"},"ReceiptNo":{"type":"string","example":"LGR919G2AV"},"TransactionReason":{"type":"string","example":"Transaction Reason"},"TransactionStatus":{"type":"string","example":"Completed"}},"example":{"Amount":10,"ConversationID":"AG_20170727_00004492b1b6d0078fbe","CreditPartyName":"254708374149 - John Doe","DebitAccountType":"Utility Account","DebitPartyCharges":"Fee For B2C Payment|KES|33.00","DebitPartyName":"600134 - Safaricom157","FinalisedTime":"20170727101415","InitiatedTime":"20170727101415","Originator Conversation ID":"19455-773836-1","ReasonType":"Salary Payment via API","ReceiptNo":"LGR919G2AV","TransactionReason":"Transaction Reason","TransactionStatus":"Completed"}},"ValidationResult":{"title":"ValidationResult","type":"object","properties":{"BillRefNumber":{"type":"string","description":"Account number for which the customer is making the payment","example":"hze","maxLength":20},"BusinessShortCode":{"type":"integer","description":"Organizations shortcode (Paybill or Buygoods)","example":654321,"format":"int64"},"FirstName":{"type":"string","description":"First Name of the customer making the payment.","example":"John"},"InvoiceNumber":{"type":"string","example":"Earum ratione velit sed."},"LastName":{"type":"string","description":"Last Name of the customer making payment.","example":"Jane"},"MSISDN":{"type":"integer","description":"Mobile number of the customer making the payment.","example":727465608550209988,"format":"int64"},"MiddleName":{"type":"string","description":"Middle Name of the customer making the payment.","example":"Doe"},"OrgAccountBalance":{"type":"integer","description":"Current utility account balance of the payment receiving organization shortcode","example":30671,"format":"int64"},"ThirdPartyTransID":{"type":"string","example":"Sapiente sed quis corrupti ut et."},"TransAmount":{"type":"integer","description":"The Amount transacted normally a numeric value","example":100,"format":"int64"},"TransID":{"type":"string","description":"Unique M-Pesa transaction ID for every payment request","example":"LHG31AA5TX"},"TransTime":{"type":"string","description":"Timestamp of the transaction","example":"20180713154301","format":"date-time"},"TransactionType":{"type":"string","description":"Transaction type specified during the payment request.","example":"Buy Goods","enum":["Buy Goods","Pay Bill"]}},"example":{"BillRefNumber":"3w2","BusinessShortCode":654321,"FirstName":"John","InvoiceNumber":"Eum et sequi optio omnis et nihil.","LastName":"Jane","MSISDN":4538922253734287447,"MiddleName":"Doe","OrgAccountBalance":30671,"ThirdPartyTransID":"Delectus repellendus sapiente dolor aut.","TransAmount":100,"TransID":"LHG31AA5TX","TransTime":"20180713154301","TransactionType":"Pay Bill"}}}}